[{"id":"97795561182","city":"Berlin","postcode":"12679","employees":"0 Beschäftigte","branch":"Vermittlung von Immobiliendarlehen","top_branch":"Mit Finanz- und Versicherungsdienstleistungen verbundene Tätigkeiten","type":"im Handelsregister eingetragen","age":"28","planungsraum":"Ahrensfelder Berge","lat":52.551192753,"lng":13.576942532},{"id":"190953561814","city":"Berlin","postcode":"12679","employees":"0 Beschäftigte","branch":"Erbringung von allen anderen überwiegend persönlichen Dienstleistungen a. n. g.","top_branch":"Erbringung von überwiegend persönlichen Dienstleistungen","type":"im Handelsregister eingetragen","age":"26","planungsraum":"Ahrensfelder Berge","lat":52.552882524,"lng":13.579957377},{"id":"183768561074","city":"Berlin","postcode":"12679","employees":"0 Beschäftigte","branch":"Einzelhandel mit Zeitschriften und Zeitungen","top_branch":"Einzelhandel","type":"im Handelsregister eingetragen","age":"12","planungsraum":"Ahrensfelder Berge","lat":52.549941227,"lng":13.575531926},{"id":"215497561990","city":"Berlin","postcode":"12679","employees":"0 Beschäftigte","branch":"Tätigkeiten von Versicherungsvertreterinnen und -vertretern","top_branch":"Mit Finanz- und Versicherungsdienstleistungen verbundene Tätigkeiten","type":"im Handelsregister eingetragen","age":"25","planungsraum":"Ahrensfelder Berge","lat":52.54864697,"lng":13.573224058},{"id":"26023306932","city":"Berlin","postcode":"12679","employees":"10 - 19 Beschäftigte","branch":"Apotheken","top_branch":"Einzelhandel","type":"Kleingewerbetreibender","age":"29","planungsraum":"Ahrensfelder Berge","lat":52.54990004,"lng":13.577331022},{"id":"278815061260","city":"Berlin","postcode":"12679","employees":"0 Beschäftigte","branch":"Ablesen, erstellen von Versorgungszählern","top_branch":"Erbringung von wirtschaftlichen Dienstleistungen für Unternehmen und Privatpersonen","type":"im Handelsregister eingetragen","age":"23","planungsraum":"Ahrensfelder Berge","lat":52.552695252,"lng":13.576560099},{"id":"37666406656","city":"Berlin","postcode":"12679","employees":"0 Beschäftigte","branch":"Sport- und Freizeitunterricht","top_branch":"Erziehung und Unterricht","type":"im Handelsregister eingetragen","age":"20","planungsraum":"Ahrensfelder Berge","lat":52.553892602,"lng":13.575138058},{"id":"408997561990","city":"Berlin","postcode":"12679","employees":"1 - 3 Beschäftigte","branch":"Einzelhandel mit Textilien","top_branch":"Einzelhandel","type":"Kleingewerbetreibender","age":"19","planungsraum":"Ahrensfelder Berge","lat":52.549456609,"lng":13.579167864},{"id":"403273061092","city":"Berlin","postcode":"12679","employees":"0 Beschäftigte","branch":"Erbringung von Beratungsleistungen auf dem Gebiet der Informationstechnologie","top_branch":"Erbringung von Dienstleistungen der Informationstechnologie","type":"im Handelsregister eingetragen","age":"20","planungsraum":"Ahrensfelder Berge","lat":52.551291113,"lng":13.581941875},{"id":"418485561942","city":"Berlin","postcode":"12679","employees":"0 Beschäftigte","branch":"Einzelhandel mit Textilien","top_branch":"Einzelhandel","type":"im Handelsregister eingetragen","age":"19","planungsraum":"Ahrensfelder Berge","lat":52.553010536,"lng":13.577543478},{"id":"42006656266","city":"Berlin","postcode":"12679","employees":"1 - 3 Beschäftigte","branch":"Erbringung von Reservierungsdienstleistungen für Theater-, Sport- und Unterhaltungsveranstaltungen","top_branch":"Erbringung von wirtschaftlichen Dienstleistungen für Unternehmen und Privatpersonen","type":"Kleingewerbetreibender","age":"19","planungsraum":"Ahrensfelder Berge","lat":52.550135034,"lng":13.584306483},{"id":"440887061548","city":"Berlin","postcode":"12679","employees":"0 Beschäftigte","branch":"Schankwirtschaften","top_branch":"Gastronomie","type":"im Handelsregister eingetragen","age":"19","planungsraum":"Ahrensfelder Berge","lat":52.549643652,"lng":13.579117278},{"id":"43614006560","city":"Berlin","postcode":"12679","employees":"0 Beschäftigte","branch":"Sekretariats- und Schreibdienste, Copy-Shops","top_branch":"Erbringung von wirtschaftlichen Dienstleistungen für Unternehmen und Privatpersonen","type":"im Handelsregister eingetragen","age":"19","planungsraum":"Ahrensfelder Berge","lat":52.550465226,"lng":13.577417864},{"id":"434489061956","city":"Berlin","postcode":"12679","employees":"0 Beschäftigte","branch":"Erbringung von allen anderen überwiegend persönlichen Dienstleistungen a. n. g.","top_branch":"Erbringung von überwiegend persönlichen Dienstleistungen","type":"im Handelsregister eingetragen","age":"19","planungsraum":"Ahrensfelder Berge","lat":52.552695252,"lng":13.576560099},{"id":"43606006240","city":"Berlin","postcode":"12679","employees":"0 Beschäftigte","branch":"Herstellung von Spielwaren","top_branch":"Herstellung von sonstigen Waren","type":"im Handelsregister eingetragen","age":"19","planungsraum":"Ahrensfelder Berge","lat":52.551901411,"lng":13.581982077},{"id":"481432561730","city":"Berlin","postcode":"12679","employees":"0 Beschäftigte","branch":"Organisation, Abbrennen von Feuerwerk","top_branch":"Erbringung von Dienstleistungen des Sports, der Unterhaltung und der Erholung","type":"im Handelsregister eingetragen","age":"18","planungsraum":"Ahrensfelder Berge","lat":52.551723488,"lng":13.580924371},{"id":"4765205682","city":"Berlin","postcode":"12679","employees":"0 Beschäftigte","branch":"Tätigkeiten von Versicherungsvertreterinnen und -vertretern","top_branch":"Mit Finanz- und Versicherungsdienstleistungen verbundene Tätigkeiten","type":"im Handelsregister eingetragen","age":"18","planungsraum":"Ahrensfelder Berge","lat":52.553536726,"lng":13.576031881},{"id":"112285267842","city":"Berlin","postcode":"12679","employees":"0 Beschäftigte","branch":"Tätigkeiten von Versicherungsvertreterinnen und -vertretern","top_branch":"Mit Finanz- und Versicherungsdienstleistungen verbundene Tätigkeiten","type":"im Handelsregister eingetragen","age":"34","planungsraum":"Ahrensfelder Berge","lat":52.550515703,"lng":13.575888618},{"id":"143826487216","city":"Berlin","postcode":"12679","employees":"1 - 3 Beschäftigte","branch":"Tätigkeiten von Versicherungsvertreterinnen und -vertretern","top_branch":"Mit Finanz- und Versicherungsdienstleistungen verbundene Tätigkeiten","type":"im Handelsregister eingetragen","age":"34","planungsraum":"Ahrensfelder Berge","lat":52.554416478,"lng":13.575349048},{"id":"1441723871746","city":"Berlin","postcode":"12679","employees":"0 Beschäftigte","branch":"Tätigkeiten der Großhandelsvermittlung von Waren ohne ausgeprägten Schwerpunkt","top_branch":"Großhandel","type":"im Handelsregister eingetragen","age":"34","planungsraum":"Ahrensfelder Berge","lat":52.549963143,"lng":13.576657007},{"id":"1783095071650","city":"Berlin","postcode":"12679","employees":"0 Beschäftigte","branch":"Tätigkeiten von Versicherungsvertreterinnen und -vertretern","top_branch":"Mit Finanz- und Versicherungsdienstleistungen verbundene Tätigkeiten","type":"im Handelsregister eingetragen","age":"33","planungsraum":"Ahrensfelder Berge","lat":52.552713705,"lng":13.574794019},{"id":"16140054718","city":"Berlin","postcode":"12679","employees":"1 - 3 Beschäftigte","branch":"Erlaubnisfreier Straßengüterverkehr (ohne Umzugstransporte)","top_branch":"Landverkehr und Transport in Rohrfernleitungen","type":"im Handelsregister eingetragen","age":"33","planungsraum":"Ahrensfelder Berge","lat":52.552166336,"lng":13.577838345},{"id":"1594708871696","city":"Berlin","postcode":"12679","employees":"20 - 49 Beschäftigte","branch":"Vermietung, Verpachtung von eigenen oder geleasten Wohngrundstücken, Wohngebäuden und Wohnungen","top_branch":"Grundstücks- und Wohnungswesen","type":"Kleingewerbetreibender","age":"49","planungsraum":"Ahrensfelder Berge","lat":52.548740933,"lng":13.573938967},{"id":"1814967671892","city":"Berlin","postcode":"12679","employees":"0 Beschäftigte","branch":"Erbringung von allen anderen überwiegend persönlichen Dienstleistungen a. n. g.","top_branch":"Erbringung von überwiegend persönlichen Dienstleistungen","type":"im Handelsregister eingetragen","age":"33","planungsraum":"Ahrensfelder Berge","lat":52.548226161,"lng":13.573077173},{"id":"20052252784","city":"Berlin","postcode":"12679","employees":"0 Beschäftigte","branch":"Tätigkeiten von Versicherungsvertreterinnen und -vertretern","top_branch":"Mit Finanz- und Versicherungsdienstleistungen verbundene Tätigkeiten","type":"im Handelsregister eingetragen","age":"32","planungsraum":"Ahrensfelder Berge","lat":52.548226161,"lng":13.573077173},{"id":"82526827894","city":"Berlin","postcode":"12679","employees":"0 Beschäftigte","branch":"Montage, Installation und Aufbau von Ständen auf Märkten, Ausstellungen und Messen","top_branch":"Vorbereitende Baustellenarbeiten, Bauinstallation und sonstiges Ausbaugewerbe","type":"im Handelsregister eingetragen","age":"12","planungsraum":"Ahrensfelder Berge","lat":52.552946436,"lng":13.574878633},{"id":"614260871536","city":"Berlin","postcode":"12679","employees":"0 Beschäftigte","branch":"Einzelhandel mit Sammlerobjekten (Briefmarken, Münzen u.ä.)","top_branch":"Einzelhandel","type":"im Handelsregister eingetragen","age":"17","planungsraum":"Ahrensfelder Berge","lat":52.552695252,"lng":13.576560099},{"id":"60918307610","city":"Berlin","postcode":"12679","employees":"0 Beschäftigte","branch":"Grafikdesign, Fotodesign","top_branch":"Sonstige wissenschaftliche und technische Tätigkeiten","type":"im Handelsregister eingetragen","age":"17","planungsraum":"Ahrensfelder Berge","lat":52.548118081,"lng":13.57626472},{"id":"61749307310","city":"Berlin","postcode":"12679","employees":"0 Beschäftigte","branch":"Erlaubnisfreier Straßengüterverkehr (ohne Umzugstransporte)","top_branch":"Landverkehr und Transport in Rohrfernleitungen","type":"im Handelsregister eingetragen","age":"18","planungsraum":"Ahrensfelder Berge","lat":52.552410916,"lng":13.575873484},{"id":"620736071120","city":"Berlin","postcode":"12679","employees":"0 Beschäftigte","branch":"Technisches Zeichenbüro","top_branch":"Tätigkeiten von Architektur- und Ingenieurbüros, technische, physikalische und chemische Untersuchung","type":"im Handelsregister eingetragen","age":"27","planungsraum":"Ahrensfelder Berge","lat":52.550344823,"lng":13.580429254},{"id":"66557647588","city":"Berlin","postcode":"12679","employees":"0 Beschäftigte","branch":"Organisationen der Bildung, Wissenschaft und Forschung","top_branch":"Interessenvertretungen sowie kirchliche und sonstige religiöse Vereinigungen, ohne Sozialwesen und Sport","type":"Kleingewerbetreibender","age":"18","planungsraum":"Ahrensfelder Berge","lat":52.551296536,"lng":13.583401671},{"id":"65774647488","city":"Berlin","postcode":"12679","employees":"0 Beschäftigte","branch":"Einzelhandel mit Waren verschiedener Art, Hauptrichtung Nicht-Nahrungsmittel","top_branch":"Einzelhandel","type":"im Handelsregister eingetragen","age":"16","planungsraum":"Ahrensfelder Berge","lat":52.550829582,"lng":13.582844194},{"id":"683351471838","city":"Berlin","postcode":"12679","employees":"0 Beschäftigte","branch":"Einzelhandel mit Waren verschiedener Art, Hauptrichtung Nicht-Nahrungsmittel","top_branch":"Einzelhandel","type":"im Handelsregister eingetragen","age":"16","planungsraum":"Ahrensfelder Berge","lat":52.551650884,"lng":13.57987034},{"id":"67935847528","city":"Berlin","postcode":"12679","employees":"0 Beschäftigte","branch":"Entwicklung und Programmierung von Internetpräsentationen","top_branch":"Erbringung von Dienstleistungen der Informationstechnologie","type":"im Handelsregister eingetragen","age":"16","planungsraum":"Ahrensfelder Berge","lat":52.552166025,"lng":13.581470197},{"id":"70514167472","city":"Berlin","postcode":"12679","employees":"1 - 3 Beschäftigte","branch":"Reparatur von Windschutzscheiben","top_branch":"Reparatur und Instandhaltung von Datenverarbeitungsgeräten und Gebrauchsgütern sowie von Kraftwagen und Krafträdern","type":"Kleingewerbetreibender","age":"15","planungsraum":"Ahrensfelder Berge","lat":52.549967495,"lng":13.583463593},{"id":"7020060720","city":"Berlin","postcode":"12679","employees":"0 Beschäftigte","branch":"Sonstiger Einzelhandel mit Waren verschiedener Art, Hauptrichtung Nahrungs- und Genussmittel und Getränken","top_branch":"Einzelhandel","type":"Kleingewerbetreibender","age":"15","planungsraum":"Ahrensfelder Berge","lat":52.549986319,"lng":13.578693075},{"id":"710979071930","city":"Berlin","postcode":"12679","employees":"1 - 3 Beschäftigte","branch":"Einzelhandel mit Zeitschriften und Zeitungen","top_branch":"Einzelhandel","type":"im Handelsregister eingetragen","age":"15","planungsraum":"Ahrensfelder Berge","lat":52.54990004,"lng":13.577331022},{"id":"72867487916","city":"Berlin","postcode":"12679","employees":"0 Beschäftigte","branch":"Promotion","top_branch":"Werbung und Marktforschung sowie Public-Relations-Beratung","type":"im Handelsregister eingetragen","age":"14","planungsraum":"Ahrensfelder Berge","lat":52.547707876,"lng":13.574652515},{"id":"74403067102","city":"Berlin","postcode":"12679","employees":"0 Beschäftigte","branch":"Erbringung von sonstigen Dienstleistungen der Informationstechnologie","top_branch":"Erbringung von Dienstleistungen der Informationstechnologie","type":"im Handelsregister eingetragen","age":"14","planungsraum":"Ahrensfelder Berge","lat":52.552516982,"lng":13.580609424},{"id":"74967427914","city":"Berlin","postcode":"12679","employees":"7 - 9 Beschäftigte","branch":"Einzelhandel mit Nahrungs- und Genussmitteln und Getränken, ohne ausgeprägten Schwerpunkt","top_branch":"Einzelhandel","type":"Kleingewerbetreibender","age":"14","planungsraum":"Ahrensfelder Berge","lat":52.54990004,"lng":13.577331022},{"id":"76162747758","city":"Berlin","postcode":"12679","employees":"0 Beschäftigte","branch":"Tätigkeiten von Werbeagenturen","top_branch":"Werbung und Marktforschung sowie Public-Relations-Beratung","type":"im Handelsregister eingetragen","age":"14","planungsraum":"Ahrensfelder Berge","lat":52.552819708,"lng":13.576603955},{"id":"770781071270","city":"Berlin","postcode":"12679","employees":"0 Beschäftigte","branch":"Promotion","top_branch":"Werbung und Marktforschung sowie Public-Relations-Beratung","type":"im Handelsregister eingetragen","age":"14","planungsraum":"Ahrensfelder Berge","lat":52.55423424,"lng":13.577473788},{"id":"773265071550","city":"Berlin","postcode":"12679","employees":"0 Beschäftigte","branch":"Erlaubnisfreier Straßengüterverkehr (ohne Umzugstransporte)","top_branch":"Landverkehr und Transport in Rohrfernleitungen","type":"im Handelsregister eingetragen","age":"14","planungsraum":"Ahrensfelder Berge","lat":52.552640528,"lng":13.579773431},{"id":"78203527784","city":"Berlin","postcode":"12679","employees":"0 Beschäftigte","branch":"Einzelcoaching, Teamcoaching","top_branch":"Erziehung und Unterricht","type":"im Handelsregister eingetragen","age":"13","planungsraum":"Ahrensfelder Berge","lat":52.552384594,"lng":13.576064553},{"id":"78543847128","city":"Berlin","postcode":"12679","employees":"0 Beschäftigte","branch":"Tätigkeiten der Großhandelsvermittlung von sonstigen Nahrungsmitteln, Getränken und Tabakwaren","top_branch":"Großhandel","type":"im Handelsregister eingetragen","age":"13","planungsraum":"Ahrensfelder Berge","lat":52.553752484,"lng":13.575086653},{"id":"790183271944","city":"Berlin","postcode":"12679","employees":"0 Beschäftigte","branch":"Güterbeförderung im Straßenverkehr","top_branch":"Landverkehr und Transport in Rohrfernleitungen","type":"im Handelsregister eingetragen","age":"16","planungsraum":"Ahrensfelder Berge","lat":52.547443816,"lng":13.574192832},{"id":"805513271044","city":"Berlin","postcode":"12679","employees":"1 - 3 Beschäftigte","branch":"Event-Caterer","top_branch":"Gastronomie","type":"Kleingewerbetreibender","age":"13","planungsraum":"Ahrensfelder Berge","lat":52.555477054,"lng":13.577410606},{"id":"821341871806","city":"Berlin","postcode":"12679","employees":"0 Beschäftigte","branch":"Installation von Solaranlagen, Photovoltaikanlagen","top_branch":"Vorbereitende Baustellenarbeiten, Bauinstallation und sonstiges Ausbaugewerbe","type":"im Handelsregister eingetragen","age":"13","planungsraum":"Ahrensfelder Berge","lat":52.553107277,"lng":13.574937879},{"id":"82049227974","city":"Berlin","postcode":"12679","employees":"0 Beschäftigte","branch":"Promotion","top_branch":"Werbung und Marktforschung sowie Public-Relations-Beratung","type":"im Handelsregister eingetragen","age":"13","planungsraum":"Ahrensfelder Berge","lat":52.554036157,"lng":13.576555447},{"id":"83168287276","city":"Berlin","postcode":"12679","employees":"0 Beschäftigte","branch":"Einzelhandel mit Blumen, Pflanzen, Sämereien und Düngemitteln","top_branch":"Einzelhandel","type":"im Handelsregister eingetragen","age":"12","planungsraum":"Ahrensfelder Berge","lat":52.548207594,"lng":13.576988329},{"id":"83235907530","city":"Berlin","postcode":"12679","employees":"0 Beschäftigte","branch":"Erbringung von sonstigen Informationsdienstleistungen","top_branch":"Datenverarbeitung, Hosting und Erbringung sonstiger Informationsdienstleistungen","type":"im Handelsregister eingetragen","age":"15","planungsraum":"Ahrensfelder Berge","lat":52.550019302,"lng":13.57482763},{"id":"836987471958","city":"Berlin","postcode":"12679","employees":"0 Beschäftigte","branch":"Trainer, Sportlehrer","top_branch":"Erziehung und Unterricht","type":"im Handelsregister eingetragen","age":"12","planungsraum":"Ahrensfelder Berge","lat":52.552410925,"lng":13.5758735},{"id":"842749271164","city":"Berlin","postcode":"12679","employees":"0 Beschäftigte","branch":"Eventmanagement","top_branch":"Erbringung von Dienstleistungen des Sports, der Unterhaltung und der Erholung","type":"im Handelsregister eingetragen","age":"12","planungsraum":"Ahrensfelder Berge","lat":52.551192753,"lng":13.576942532},{"id":"851328671762","city":"Berlin","postcode":"12679","employees":"0 Beschäftigte","branch":"Literarisches Schaffen und Musikkomposition","top_branch":"Kunstschaffende Tätigkeiten und Tätigkeiten in der darstellenden Kunst","type":"im Handelsregister eingetragen","age":"13","planungsraum":"Ahrensfelder Berge","lat":52.554705723,"lng":13.575680369},{"id":"851781671272","city":"Berlin","postcode":"12679","employees":"0 Beschäftigte","branch":"Tätigkeiten von Versicherungsvertreterinnen und -vertretern","top_branch":"Mit Finanz- und Versicherungsdienstleistungen verbundene Tätigkeiten","type":"im Handelsregister eingetragen","age":"12","planungsraum":"Ahrensfelder Berge","lat":52.552713697,"lng":13.574794004},{"id":"85462267742","city":"Berlin","postcode":"12679","employees":"0 Beschäftigte","branch":"Veröffentlichung von Musikaufnahmen (Labels)","top_branch":"Herstellung, Verleih und Vertrieb von Filmen und Fernsehprogrammen, Kinos, Tonstudios und Verlegen von Musik","type":"im Handelsregister eingetragen","age":"12","planungsraum":"Ahrensfelder Berge","lat":52.54885907,"lng":13.578468561},{"id":"859556471188","city":"Berlin","postcode":"12679","employees":"0 Beschäftigte","branch":"Beratung Umweltschutz und Nachhaltigkeit","top_branch":"Sonstige wissenschaftliche und technische Tätigkeiten","type":"im Handelsregister eingetragen","age":"12","planungsraum":"Ahrensfelder Berge","lat":52.551296536,"lng":13.583401671},{"id":"85945387846","city":"Berlin","postcode":"12679","employees":"0 Beschäftigte","branch":"Abbrucharbeiten","top_branch":"Vorbereitende Baustellenarbeiten, Bauinstallation und sonstiges Ausbaugewerbe","type":"im Handelsregister eingetragen","age":"12","planungsraum":"Ahrensfelder Berge","lat":52.552210195,"lng":13.580175749},{"id":"869398271994","city":"Berlin","postcode":"12679","employees":"0 Beschäftigte","branch":"Dienstleistung im Gastgewerbe","top_branch":"Erbringung von überwiegend persönlichen Dienstleistungen","type":"im Handelsregister eingetragen","age":"12","planungsraum":"Ahrensfelder Berge","lat":52.547655156,"lng":13.574964173},{"id":"87805867862","city":"Berlin","postcode":"12679","employees":"0 Beschäftigte","branch":"Büroservice","top_branch":"Erbringung von wirtschaftlichen Dienstleistungen für Unternehmen und Privatpersonen","type":"im Handelsregister eingetragen","age":"11","planungsraum":"Ahrensfelder Berge","lat":52.550629244,"lng":13.575009733},{"id":"881964071880","city":"Berlin","postcode":"12679","employees":"0 Beschäftigte","branch":"Einzelhandel mit zoologischem Bedarf und lebenden Tieren","top_branch":"Einzelhandel","type":"im Handelsregister eingetragen","age":"11","planungsraum":"Ahrensfelder Berge","lat":52.553517291,"lng":13.578101947},{"id":"89369767992","city":"Berlin","postcode":"12679","employees":"0 Beschäftigte","branch":"Durchführung von Veranstaltungen, Veranstaltungsservice","top_branch":"Erbringung von Dienstleistungen des Sports, der Unterhaltung und der Erholung","type":"im Handelsregister eingetragen","age":"11","planungsraum":"Ahrensfelder Berge","lat":52.549645357,"lng":13.580787758},{"id":"895137071790","city":"Berlin","postcode":"12679","employees":"0 Beschäftigte","branch":"Sonstiges Verlagswesen, ohne Software","top_branch":"Verlagswesen","type":"im Handelsregister eingetragen","age":"17","planungsraum":"Ahrensfelder Berge","lat":52.553517291,"lng":13.578101947},{"id":"90193327444","city":"Berlin","postcode":"12679","employees":"0 Beschäftigte","branch":"Tätigkeiten von Versicherungsvertreterinnen und -vertretern","top_branch":"Mit Finanz- und Versicherungsdienstleistungen verbundene Tätigkeiten","type":"im Handelsregister eingetragen","age":"11","planungsraum":"Ahrensfelder Berge","lat":52.554686664,"lng":13.575818664},{"id":"90197287576","city":"Berlin","postcode":"12679","employees":"0 Beschäftigte","branch":"Personenbeförderung mit Fahrzeug mit Fahrer auf Abruf","top_branch":"Landverkehr und Transport in Rohrfernleitungen","type":"im Handelsregister eingetragen","age":"11","planungsraum":"Ahrensfelder Berge","lat":52.553931094,"lng":13.576168649},{"id":"90964627154","city":"Berlin","postcode":"12679","employees":"0 Beschäftigte","branch":"Betreuungsdienste für Heimtiere","top_branch":"Erbringung von überwiegend persönlichen Dienstleistungen","type":"im Handelsregister eingetragen","age":"11","planungsraum":"Ahrensfelder Berge","lat":52.551650884,"lng":13.57987034},{"id":"917187671292","city":"Berlin","postcode":"12679","employees":"0 Beschäftigte","branch":"Durchführung von Veranstaltungen, Veranstaltungsservice","top_branch":"Erbringung von Dienstleistungen des Sports, der Unterhaltung und der Erholung","type":"im Handelsregister eingetragen","age":"11","planungsraum":"Ahrensfelder Berge","lat":52.548697127,"lng":13.579447621},{"id":"92426287876","city":"Berlin","postcode":"12679","employees":"0 Beschäftigte","branch":"Dienstleistungen im Veranstaltungsbereich","top_branch":"Kunstschaffende Tätigkeiten und Tätigkeiten in der darstellenden Kunst","type":"im Handelsregister eingetragen","age":"10","planungsraum":"Ahrensfelder Berge","lat":52.549357991,"lng":13.581244191},{"id":"93004747158","city":"Berlin","postcode":"12679","employees":"0 Beschäftigte","branch":"Discjockey, Moderation","top_branch":"Kunstschaffende Tätigkeiten und Tätigkeiten in der darstellenden Kunst","type":"im Handelsregister eingetragen","age":"10","planungsraum":"Ahrensfelder Berge","lat":52.547846369,"lng":13.57308353},{"id":"942547271824","city":"Berlin","postcode":"12679","employees":"0 Beschäftigte","branch":"Hausmeisterdienste","top_branch":"Gebäudebetreuung, Garten- und Landschaftsbau","type":"im Handelsregister eingetragen","age":"10","planungsraum":"Ahrensfelder Berge","lat":52.553588032,"lng":13.575110431},{"id":"94285807860","city":"Berlin","postcode":"12679","employees":"0 Beschäftigte","branch":"Nagelstudio","top_branch":"Erbringung von überwiegend persönlichen Dienstleistungen","type":"im Handelsregister eingetragen","age":"10","planungsraum":"Ahrensfelder Berge","lat":52.547846369,"lng":13.57308353},{"id":"942559871866","city":"Berlin","postcode":"12679","employees":"0 Beschäftigte","branch":"Sekretariats- und Schreibdienste, Copy-Shops","top_branch":"Erbringung von wirtschaftlichen Dienstleistungen für Unternehmen und Privatpersonen","type":"im Handelsregister eingetragen","age":"10","planungsraum":"Ahrensfelder Berge","lat":52.548697127,"lng":13.579447621},{"id":"942927071090","city":"Berlin","postcode":"12679","employees":"0 Beschäftigte","branch":"Mietkoch","top_branch":"Gastronomie","type":"im Handelsregister eingetragen","age":"10","planungsraum":"Ahrensfelder Berge","lat":52.552410916,"lng":13.575873484},{"id":"945379271264","city":"Berlin","postcode":"12679","employees":"10 - 19 Beschäftigte","branch":"Einzelhandel mit Nahrungs- und Genussmitteln und Getränken, ohne ausgeprägten Schwerpunkt","top_branch":"Einzelhandel","type":"Kleingewerbetreibender","age":"10","planungsraum":"Ahrensfelder Berge","lat":52.549986319,"lng":13.578693075},{"id":"949084871616","city":"Berlin","postcode":"12679","employees":"0 Beschäftigte","branch":"Lieferdienste","top_branch":"Post-, Kurier- und Expressdienste","type":"im Handelsregister eingetragen","age":"10","planungsraum":"Ahrensfelder Berge","lat":52.551192753,"lng":13.576942532},{"id":"95299507650","city":"Berlin","postcode":"12679","employees":"0 Beschäftigte","branch":"Desinfektion und Schädlingsbekämpfung","top_branch":"Gebäudebetreuung, Garten- und Landschaftsbau","type":"im Handelsregister eingetragen","age":"10","planungsraum":"Ahrensfelder Berge","lat":52.549357991,"lng":13.581244191},{"id":"959200871336","city":"Berlin","postcode":"12679","employees":"0 Beschäftigte","branch":"Alle anderen Tätigkeiten typischerweise freiberuflicher, wissenschaftlicher oder technischer Art a. n. g. (ohne Künstler- und Modelagenturen)","top_branch":"Sonstige wissenschaftliche und technische Tätigkeiten","type":"im Handelsregister eingetragen","age":"9","planungsraum":"Ahrensfelder Berge","lat":52.552073146,"lng":13.578457207},{"id":"965247671492","city":"Berlin","postcode":"12679","employees":"0 Beschäftigte","branch":"Promotion","top_branch":"Werbung und Marktforschung sowie Public-Relations-Beratung","type":"im Handelsregister eingetragen","age":"9","planungsraum":"Ahrensfelder Berge","lat":52.550576211,"lng":13.579716584},{"id":"97635967532","city":"Berlin","postcode":"12679","employees":"0 Beschäftigte","branch":"Unternehmensberatung","top_branch":"Verwaltung und Führung von Unternehmen und Betrieben, Unternehmensberatung","type":"im Handelsregister eingetragen","age":"9","planungsraum":"Ahrensfelder Berge","lat":52.550019302,"lng":13.57482763},{"id":"977884871616","city":"Berlin","postcode":"12679","employees":"0 Beschäftigte","branch":"Sonstiger Einzelhandel mit Waren verschiedener Art","top_branch":"Einzelhandel","type":"im Handelsregister eingetragen","age":"11","planungsraum":"Ahrensfelder Berge","lat":52.552073146,"lng":13.578457207},{"id":"983134871116","city":"Berlin","postcode":"12679","employees":"0 Beschäftigte","branch":"Mietkoch","top_branch":"Gastronomie","type":"im Handelsregister eingetragen","age":"9","planungsraum":"Ahrensfelder Berge","lat":52.552313905,"lng":13.5803228},{"id":"98946247208","city":"Berlin","postcode":"12679","employees":"0 Beschäftigte","branch":"Kontaktgeber, Tippgeber, Anschriftenvermittlung","top_branch":"Erbringung von wirtschaftlichen Dienstleistungen für Unternehmen und Privatpersonen","type":"im Handelsregister eingetragen","age":"9","planungsraum":"Ahrensfelder Berge","lat":52.550785959,"lng":13.57597586},{"id":"1037210471368","city":"Berlin","postcode":"12679","employees":"0 Beschäftigte","branch":"Discjockey, Moderation","top_branch":"Kunstschaffende Tätigkeiten und Tätigkeiten in der darstellenden Kunst","type":"im Handelsregister eingetragen","age":"8","planungsraum":"Ahrensfelder Berge","lat":52.553003737,"lng":13.579037303},{"id":"1098375071250","city":"Berlin","postcode":"12679","employees":"0 Beschäftigte","branch":"Programmierungstätigkeiten a. n. g.","top_branch":"Erbringung von Dienstleistungen der Informationstechnologie","type":"im Handelsregister eingetragen","age":"10","planungsraum":"Ahrensfelder Berge","lat":52.549456609,"lng":13.579167864},{"id":"10212288796","city":"Berlin","postcode":"12679","employees":"0 Beschäftigte","branch":"Erbringung von sonstigen überwiegend persönlichen Dienstleistungen a. n. g.","top_branch":"Erbringung von überwiegend persönlichen Dienstleistungen","type":"im Handelsregister eingetragen","age":"12","planungsraum":"Ahrensfelder Berge","lat":52.552517946,"lng":13.579592114},{"id":"100404907830","city":"Berlin","postcode":"12679","employees":"0 Beschäftigte","branch":"Akustik- und Trockenbau","top_branch":"Vorbereitende Baustellenarbeiten, Bauinstallation und sonstiges Ausbaugewerbe","type":"im Handelsregister eingetragen","age":"8","planungsraum":"Ahrensfelder Berge","lat":52.553517299,"lng":13.578101963},{"id":"1034701871006","city":"Berlin","postcode":"12679","employees":"0 Beschäftigte","branch":"Rettungs- und Krankentransportdienste","top_branch":"Gesundheitswesen","type":"im Handelsregister eingetragen","age":"8","planungsraum":"Ahrensfelder Berge","lat":52.553340909,"lng":13.578809679},{"id":"101410267342","city":"Berlin","postcode":"12679","employees":"0 Beschäftigte","branch":"Erbringung von sonstigen überwiegend persönlichen Dienstleistungen a. n. g.","top_branch":"Erbringung von überwiegend persönlichen Dienstleistungen","type":"im Handelsregister eingetragen","age":"22","planungsraum":"Ahrensfelder Berge","lat":52.548697136,"lng":13.579447622},{"id":"102969427314","city":"Berlin","postcode":"12679","employees":"1 - 3 Beschäftigte","branch":"Einzelhandel mit Software","top_branch":"Einzelhandel","type":"Kleingewerbetreibender","age":"8","planungsraum":"Ahrensfelder Berge","lat":52.553340909,"lng":13.578809679},{"id":"1041306071020","city":"Berlin","postcode":"12679","employees":"0 Beschäftigte","branch":"Imbissstuben u. Ä.","top_branch":"Gastronomie","type":"im Handelsregister eingetragen","age":"8","planungsraum":"Ahrensfelder Berge","lat":52.549643651,"lng":13.579117277},{"id":"10176198766","city":"Berlin","postcode":"12679","employees":"0 Beschäftigte","branch":"hauswirtschaftliche Versorgung, Haushaltshilfe","top_branch":"Sozialwesen, ohne Heime","type":"im Handelsregister eingetragen","age":"8","planungsraum":"Ahrensfelder Berge","lat":52.550328168,"lng":13.583363579},{"id":"1041553271844","city":"Berlin","postcode":"12679","employees":"0 Beschäftigte","branch":"hauswirtschaftliche Versorgung, Haushaltshilfe","top_branch":"Sozialwesen, ohne Heime","type":"im Handelsregister eingetragen","age":"8","planungsraum":"Ahrensfelder Berge","lat":52.554705715,"lng":13.575680354},{"id":"1010235071450","city":"Berlin","postcode":"12679","employees":"0 Beschäftigte","branch":"Akustik- und Trockenbau","top_branch":"Vorbereitende Baustellenarbeiten, Bauinstallation und sonstiges Ausbaugewerbe","type":"im Handelsregister eingetragen","age":"8","planungsraum":"Ahrensfelder Berge","lat":52.554489857,"lng":13.577009188},{"id":"102569467982","city":"Berlin","postcode":"12679","employees":"0 Beschäftigte","branch":"Onlinemarketing","top_branch":"Werbung und Marktforschung sowie Public-Relations-Beratung","type":"im Handelsregister eingetragen","age":"8","planungsraum":"Ahrensfelder Berge","lat":52.554145141,"lng":13.577644588},{"id":"9996048716","city":"Berlin","postcode":"12679","employees":"0 Beschäftigte","branch":"Dienstleistung im Gastgewerbe","top_branch":"Erbringung von überwiegend persönlichen Dienstleistungen","type":"im Handelsregister eingetragen","age":"9","planungsraum":"Ahrensfelder Berge","lat":52.549645357,"lng":13.580787758},{"id":"100999027634","city":"Berlin","postcode":"12679","employees":"0 Beschäftigte","branch":"Kurierdienste","top_branch":"Post-, Kurier- und Expressdienste","type":"im Handelsregister eingetragen","age":"8","planungsraum":"Ahrensfelder Berge","lat":52.54864697,"lng":13.573224058},{"id":"1021567271224","city":"Berlin","postcode":"12679","employees":"0 Beschäftigte","branch":"Messe-, Kongress- und Business-Event-Veranstalter","top_branch":"Erbringung von wirtschaftlichen Dienstleistungen für Unternehmen und Privatpersonen","type":"im Handelsregister eingetragen","age":"18","planungsraum":"Ahrensfelder Berge","lat":52.550767651,"lng":13.574105169},{"id":"1048705871686","city":"Berlin","postcode":"12679","employees":"0 Beschäftigte","branch":"Einzelhandel mit sonstigen Kunst- und Kulturerzeugnissen a. n. g.","top_branch":"Einzelhandel","type":"im Handelsregister eingetragen","age":"8","planungsraum":"Ahrensfelder Berge","lat":52.552741229,"lng":13.578449983},{"id":"104907307910","city":"Berlin","postcode":"12679","employees":"0 Beschäftigte","branch":"Einzelhandel mit Waren verschiedener Art, Hauptrichtung Nicht-Nahrungsmittel","top_branch":"Einzelhandel","type":"im Handelsregister eingetragen","age":"14","planungsraum":"Ahrensfelder Berge","lat":52.552960021,"lng":13.574881687},{"id":"109143607120","city":"Berlin","postcode":"12679","employees":"0 Beschäftigte","branch":"Web-Suchportale","top_branch":"Datenverarbeitung, Hosting und Erbringung sonstiger Informationsdienstleistungen","type":"im Handelsregister eingetragen","age":"7","planungsraum":"Ahrensfelder Berge","lat":52.552984072,"lng":13.579020491},{"id":"10758054718","city":"Berlin","postcode":"12679","employees":"0 Beschäftigte","branch":"Akustik- und Trockenbau","top_branch":"Vorbereitende Baustellenarbeiten, Bauinstallation und sonstiges Ausbaugewerbe","type":"im Handelsregister eingetragen","age":"7","planungsraum":"Ahrensfelder Berge","lat":52.553892619,"lng":13.575138074},{"id":"109289527984","city":"Berlin","postcode":"12679","employees":"0 Beschäftigte","branch":"Gartenpflege","top_branch":"Gebäudebetreuung, Garten- und Landschaftsbau","type":"im Handelsregister eingetragen","age":"7","planungsraum":"Ahrensfelder Berge","lat":52.550344831,"lng":13.580429269},{"id":"1068528071760","city":"Berlin","postcode":"12679","employees":"0 Beschäftigte","branch":"Gartenpflege","top_branch":"Gebäudebetreuung, Garten- und Landschaftsbau","type":"im Handelsregister eingetragen","age":"7","planungsraum":"Ahrensfelder Berge","lat":52.552773086,"lng":13.577458092},{"id":"1055848271494","city":"Berlin","postcode":"12679","employees":"0 Beschäftigte","branch":"Einzelhandel mit Kraftwagen mit einem zulässigen Gesamtgewicht von 3,5 t oder weniger","top_branch":"Einzelhandel","type":"im Handelsregister eingetragen","age":"7","planungsraum":"Ahrensfelder Berge","lat":52.550024299,"lng":13.579269927},{"id":"1068526271754","city":"Berlin","postcode":"12679","employees":"0 Beschäftigte","branch":"Einzelhandel mit Waren verschiedener Art, Hauptrichtung Nicht-Nahrungsmittel","top_branch":"Einzelhandel","type":"im Handelsregister eingetragen","age":"7","planungsraum":"Ahrensfelder Berge","lat":52.54811809,"lng":13.576264736},{"id":"1122461471538","city":"Berlin","postcode":"12679","employees":"0 Beschäftigte","branch":"Einzelhandel mit Büchern","top_branch":"Einzelhandel","type":"im Handelsregister eingetragen","age":"6","planungsraum":"Ahrensfelder Berge","lat":52.549967504,"lng":13.583463609},{"id":"1111745471818","city":"Berlin","postcode":"12679","employees":"0 Beschäftigte","branch":"Datenbanken","top_branch":"Datenverarbeitung, Hosting und Erbringung sonstiger Informationsdienstleistungen","type":"im Handelsregister eingetragen","age":"6","planungsraum":"Ahrensfelder Berge","lat":52.548618695,"lng":13.577135805},{"id":"1105725671752","city":"Berlin","postcode":"12679","employees":"0 Beschäftigte","branch":"Web-Suchportale","top_branch":"Datenverarbeitung, Hosting und Erbringung sonstiger Informationsdienstleistungen","type":"im Handelsregister eingetragen","age":"6","planungsraum":"Ahrensfelder Berge","lat":52.553421684,"lng":13.577968851},{"id":"114737527584","city":"Berlin","postcode":"12679","employees":"unbekannt","branch":"Einzelhandel mit sonstigen Nahrungs- und Genussmitteln","top_branch":"Einzelhandel","type":"im Handelsregister eingetragen","age":"8","planungsraum":"Ahrensfelder Berge","lat":52.550629252,"lng":13.575009749},{"id":"113178547618","city":"Berlin","postcode":"12679","employees":"1 - 3 Beschäftigte","branch":"Kantinen","top_branch":"Gastronomie","type":"Kleingewerbetreibender","age":"6","planungsraum":"Ahrensfelder Berge","lat":52.55585677,"lng":13.57580813},{"id":"113710687356","city":"Berlin","postcode":"12679","employees":"0 Beschäftigte","branch":"Sonstige Vermittlungstätigkeiten für die Erbringung von wirtschaftlichen Dienstleistungen für Unternehmen und Privatpersonen a. n. g.","top_branch":"Erbringung von wirtschaftlichen Dienstleistungen für Unternehmen und Privatpersonen","type":"im Handelsregister eingetragen","age":"6","planungsraum":"Ahrensfelder Berge","lat":52.54811809,"lng":13.576264736},{"id":"1125564671882","city":"Berlin","postcode":"12679","employees":"0 Beschäftigte","branch":"Lohnsteuerhilfe","top_branch":"Rechts- und Steuerberatung, Wirtschaftsprüfung","type":"im Handelsregister eingetragen","age":"6","planungsraum":"Ahrensfelder Berge","lat":52.54786427,"lng":13.575769871},{"id":"1158563471878","city":"Berlin","postcode":"12679","employees":"0 Beschäftigte","branch":"Buchführung ohne Datenverarbeitungsdienste","top_branch":"Rechts- und Steuerberatung, Wirtschaftsprüfung","type":"im Handelsregister eingetragen","age":"5","planungsraum":"Ahrensfelder Berge","lat":52.554008761,"lng":13.576770502},{"id":"1162702271674","city":"Berlin","postcode":"12679","employees":"0 Beschäftigte","branch":"Akustik- und Trockenbau","top_branch":"Vorbereitende Baustellenarbeiten, Bauinstallation und sonstiges Ausbaugewerbe","type":"im Handelsregister eingetragen","age":"5","planungsraum":"Ahrensfelder Berge","lat":52.551786373,"lng":13.57675411},{"id":"119123647788","city":"Berlin","postcode":"12679","employees":"0 Beschäftigte","branch":"Grafikdesign, Fotodesign","top_branch":"Sonstige wissenschaftliche und technische Tätigkeiten","type":"im Handelsregister eingetragen","age":"4","planungsraum":"Ahrensfelder Berge","lat":52.551557519,"lng":13.580820848},{"id":"117500227674","city":"Berlin","postcode":"12679","employees":"0 Beschäftigte","branch":"Akustik- und Trockenbau","top_branch":"Vorbereitende Baustellenarbeiten, Bauinstallation und sonstiges Ausbaugewerbe","type":"im Handelsregister eingetragen","age":"5","planungsraum":"Ahrensfelder Berge","lat":52.554489865,"lng":13.577009204},{"id":"102190687356","city":"Berlin","postcode":"12679","employees":"0 Beschäftigte","branch":"Einzelhandel mit Hardware","top_branch":"Einzelhandel","type":"im Handelsregister eingetragen","age":"8","planungsraum":"Ahrensfelder Berge","lat":52.551218561,"lng":13.576295369},{"id":"11820066722","city":"Berlin","postcode":"12679","employees":"0 Beschäftigte","branch":"Sonstiges Drucken","top_branch":"Herstellung von Druckerzeugnissen, Vervielfältigung von bespielten Ton-, Bild- und Datenträgern","type":"im Handelsregister eingetragen","age":"5","planungsraum":"Ahrensfelder Berge","lat":52.551901419,"lng":13.581982093},{"id":"1178149271164","city":"Berlin","postcode":"12679","employees":"0 Beschäftigte","branch":"Nagelstudio","top_branch":"Erbringung von überwiegend persönlichen Dienstleistungen","type":"im Handelsregister eingetragen","age":"5","planungsraum":"Ahrensfelder Berge","lat":52.552984072,"lng":13.579020491},{"id":"1162197671992","city":"Berlin","postcode":"12679","employees":"0 Beschäftigte","branch":"Tätowier- und Piercingstudios","top_branch":"Erbringung von überwiegend persönlichen Dienstleistungen","type":"im Handelsregister eingetragen","age":"5","planungsraum":"Ahrensfelder Berge","lat":52.549700628,"lng":13.580925644},{"id":"1163817071390","city":"Berlin","postcode":"12679","employees":"0 Beschäftigte","branch":"Discjockey, Moderation","top_branch":"Kunstschaffende Tätigkeiten und Tätigkeiten in der darstellenden Kunst","type":"im Handelsregister eingetragen","age":"5","planungsraum":"Ahrensfelder Berge","lat":52.551288075,"lng":13.580737792},{"id":"117071467382","city":"Berlin","postcode":"12679","employees":"0 Beschäftigte","branch":"Überführung von einzelnen Kraftfahrzeugen","top_branch":"Lagerei sowie Erbringung von sonstigen Dienstleistungen für den Verkehr","type":"im Handelsregister eingetragen","age":"5","planungsraum":"Ahrensfelder Berge","lat":52.548073197,"lng":13.576587218},{"id":"115756927564","city":"Berlin","postcode":"12679","employees":"0 Beschäftigte","branch":"Einzelhandel mit sonstigen Gebrauchtwaren a. n. g.","top_branch":"Einzelhandel","type":"im Handelsregister eingetragen","age":"5","planungsraum":"Ahrensfelder Berge","lat":52.553106921,"lng":13.579190086},{"id":"11718222774","city":"Berlin","postcode":"12679","employees":"0 Beschäftigte","branch":"Personalberatung","top_branch":"Verwaltung und Führung von Unternehmen und Betrieben, Unternehmensberatung","type":"im Handelsregister eingetragen","age":"5","planungsraum":"Ahrensfelder Berge","lat":52.551332638,"lng":13.576976925},{"id":"1180702871676","city":"Berlin","postcode":"12679","employees":"0 Beschäftigte","branch":"Erbringung von allen anderen überwiegend persönlichen Dienstleistungen a. n. g.","top_branch":"Erbringung von überwiegend persönlichen Dienstleistungen","type":"im Handelsregister eingetragen","age":"9","planungsraum":"Ahrensfelder Berge","lat":52.550967031,"lng":13.574156704},{"id":"1212600672","city":"Berlin","postcode":"12679","employees":"0 Beschäftigte","branch":"Unternehmensberatung","top_branch":"Verwaltung und Führung von Unternehmen und Betrieben, Unternehmensberatung","type":"im Handelsregister eingetragen","age":"4","planungsraum":"Ahrensfelder Berge","lat":52.55191036,"lng":13.575879316},{"id":"1207145471818","city":"Berlin","postcode":"12679","employees":"0 Beschäftigte","branch":"Lektorat, Korrektur lesen","top_branch":"Kunstschaffende Tätigkeiten und Tätigkeiten in der darstellenden Kunst","type":"im Handelsregister eingetragen","age":"4","planungsraum":"Ahrensfelder Berge","lat":52.551307938,"lng":13.575687793},{"id":"122717767592","city":"Berlin","postcode":"12679","employees":"0 Beschäftigte","branch":"Einzelhandel mit Waren verschiedener Art, Hauptrichtung Nicht-Nahrungsmittel","top_branch":"Einzelhandel","type":"im Handelsregister eingetragen","age":"4","planungsraum":"Ahrensfelder Berge","lat":52.553517299,"lng":13.578101963},{"id":"120202807760","city":"Berlin","postcode":"12679","employees":"unbekannt","branch":"Organisationen der Bildung, Wissenschaft und Forschung","top_branch":"Interessenvertretungen sowie kirchliche und sonstige religiöse Vereinigungen, ohne Sozialwesen und Sport","type":"Kleingewerbetreibender","age":"12","planungsraum":"Ahrensfelder Berge","lat":52.551421455,"lng":13.574716517},{"id":"1224586871956","city":"Berlin","postcode":"12679","employees":"0 Beschäftigte","branch":"Akustik- und Trockenbau","top_branch":"Vorbereitende Baustellenarbeiten, Bauinstallation und sonstiges Ausbaugewerbe","type":"im Handelsregister eingetragen","age":"4","planungsraum":"Ahrensfelder Berge","lat":52.551264597,"lng":13.579698359},{"id":"121328167272","city":"Berlin","postcode":"12679","employees":"0 Beschäftigte","branch":"Erlaubnisfreier Straßengüterverkehr (ohne Umzugstransporte)","top_branch":"Landverkehr und Transport in Rohrfernleitungen","type":"im Handelsregister eingetragen","age":"4","planungsraum":"Ahrensfelder Berge","lat":52.549643651,"lng":13.579117277},{"id":"1208391671972","city":"Berlin","postcode":"12679","employees":"0 Beschäftigte","branch":"Erbringung von allen anderen Unterrichtsdienstleistungen a. n. g.","top_branch":"Erziehung und Unterricht","type":"im Handelsregister eingetragen","age":"4","planungsraum":"Ahrensfelder Berge","lat":52.548066988,"lng":13.57303407},{"id":"1222535471118","city":"Berlin","postcode":"12679","employees":"0 Beschäftigte","branch":"Entwicklung und Programmierung von Internetpräsentationen","top_branch":"Erbringung von Dienstleistungen der Informationstechnologie","type":"im Handelsregister eingetragen","age":"4","planungsraum":"Ahrensfelder Berge","lat":52.547707884,"lng":13.574652531},{"id":"120966367212","city":"Berlin","postcode":"12679","employees":"0 Beschäftigte","branch":"Onlinemarketing","top_branch":"Werbung und Marktforschung sowie Public-Relations-Beratung","type":"im Handelsregister eingetragen","age":"4","planungsraum":"Ahrensfelder Berge","lat":52.547545475,"lng":13.57355271},{"id":"131233987466","city":"Berlin","postcode":"12679","employees":"0 Beschäftigte","branch":"Reiseleiter und Gästeführer","top_branch":"Reisebüros, Reiseveranstalter und Erbringung sonstiger Reservierungsdienstleistungen","type":"im Handelsregister eingetragen","age":"2","planungsraum":"Ahrensfelder Berge","lat":52.550785968,"lng":13.575975876},{"id":"123846427214","city":"Berlin","postcode":"12679","employees":"0 Beschäftigte","branch":"Fußpflege kosmetisch","top_branch":"Erbringung von überwiegend persönlichen Dienstleistungen","type":"im Handelsregister eingetragen","age":"3","planungsraum":"Ahrensfelder Berge","lat":52.548073197,"lng":13.576587218},{"id":"125184307810","city":"Berlin","postcode":"12679","employees":"unbekannt","branch":"Ausschank von Getränken","top_branch":"Gastronomie","type":"im Handelsregister eingetragen","age":"8","planungsraum":"Ahrensfelder Berge","lat":52.547443824,"lng":13.574192848},{"id":"1255701071670","city":"Berlin","postcode":"12679","employees":"0 Beschäftigte","branch":"Herstellung von Filmwerbung","top_branch":"Herstellung, Verleih und Vertrieb von Filmen und Fernsehprogrammen, Kinos, Tonstudios und Verlegen von Musik","type":"im Handelsregister eingetragen","age":"3","planungsraum":"Ahrensfelder Berge","lat":52.548427594,"lng":13.573147275},{"id":"128065267842","city":"Berlin","postcode":"12679","employees":"0 Beschäftigte","branch":"Einzelhandel mit Waren verschiedener Art, Hauptrichtung Nicht-Nahrungsmittel","top_branch":"Einzelhandel","type":"im Handelsregister eingetragen","age":"2","planungsraum":"Ahrensfelder Berge","lat":52.552984072,"lng":13.579020491},{"id":"126321967732","city":"Berlin","postcode":"12679","employees":"0 Beschäftigte","branch":"Herstellung von sonstigen Erzeugnissen a. n. g.","top_branch":"Herstellung von sonstigen Waren","type":"im Handelsregister eingetragen","age":"3","planungsraum":"Ahrensfelder Berge","lat":52.551557519,"lng":13.580820848},{"id":"1254313871046","city":"Berlin","postcode":"12679","employees":"0 Beschäftigte","branch":"Einzelhandel mit Kinderbekleidung, Bekleidungszubehör","top_branch":"Einzelhandel","type":"im Handelsregister eingetragen","age":"5","planungsraum":"Ahrensfelder Berge","lat":52.549443457,"lng":13.580252199},{"id":"127760227674","city":"Berlin","postcode":"12679","employees":"unbekannt","branch":"Lohnsteuerhilfe","top_branch":"Rechts- und Steuerberatung, Wirtschaftsprüfung","type":"im Handelsregister eingetragen","age":"10","planungsraum":"Ahrensfelder Berge","lat":52.55061393,"lng":13.576872782},{"id":"127516507550","city":"Berlin","postcode":"12679","employees":"0 Beschäftigte","branch":"Einzelhandel mit Schreib- und Papierwaren, Schul- und Büroartikeln","top_branch":"Einzelhandel","type":"im Handelsregister eingetragen","age":"2","planungsraum":"Ahrensfelder Berge","lat":52.554421629,"lng":13.577141085},{"id":"1278507071690","city":"Berlin","postcode":"12679","employees":"0 Beschäftigte","branch":"Einzelhandel mit Waren verschiedener Art, Hauptrichtung Nicht-Nahrungsmittel","top_branch":"Einzelhandel","type":"im Handelsregister eingetragen","age":"2","planungsraum":"Ahrensfelder Berge","lat":52.548073197,"lng":13.576587218},{"id":"128848987966","city":"Berlin","postcode":"12679","employees":"0 Beschäftigte","branch":"Akustik- und Trockenbau","top_branch":"Vorbereitende Baustellenarbeiten, Bauinstallation und sonstiges Ausbaugewerbe","type":"im Handelsregister eingetragen","age":"2","planungsraum":"Ahrensfelder Berge","lat":52.550328176,"lng":13.583363595},{"id":"124875547518","city":"Berlin","postcode":"12679","employees":"0 Beschäftigte","branch":"Einzelhandel mit Waren verschiedener Art, Hauptrichtung Nicht-Nahrungsmittel","top_branch":"Einzelhandel","type":"im Handelsregister eingetragen","age":"3","planungsraum":"Ahrensfelder Berge","lat":52.548073197,"lng":13.576587218},{"id":"126246487216","city":"Berlin","postcode":"12679","employees":"0 Beschäftigte","branch":"Verwaltung von eigenen Grundstücken, Gebäuden, Wohnungen","top_branch":"Grundstücks- und Wohnungswesen","type":"Kleingewerbetreibender","age":"3","planungsraum":"Ahrensfelder Berge","lat":52.55191036,"lng":13.575879316},{"id":"128823247108","city":"Berlin","postcode":"12679","employees":"0 Beschäftigte","branch":"Direktmarketing","top_branch":"Werbung und Marktforschung sowie Public-Relations-Beratung","type":"im Handelsregister eingetragen","age":"3","planungsraum":"Ahrensfelder Berge","lat":52.551616982,"lng":13.574410488},{"id":"1283753471178","city":"Berlin","postcode":"12679","employees":"0 Beschäftigte","branch":"Einzelcoaching, Teamcoaching","top_branch":"Erziehung und Unterricht","type":"im Handelsregister eingetragen","age":"2","planungsraum":"Ahrensfelder Berge","lat":52.553053904,"lng":13.575837241},{"id":"1272308471028","city":"Berlin","postcode":"12679","employees":"0 Beschäftigte","branch":"Einzelhandel mit Waren verschiedener Art, Hauptrichtung Nicht-Nahrungsmittel","top_branch":"Einzelhandel","type":"im Handelsregister eingetragen","age":"3","planungsraum":"Ahrensfelder Berge","lat":52.551749889,"lng":13.574436205},{"id":"129562807760","city":"Berlin","postcode":"12679","employees":"0 Beschäftigte","branch":"Beteiligungsgesellschaften","top_branch":"Erbringung von Finanzdienstleistungen","type":"Kleingewerbetreibender","age":"2","planungsraum":"Ahrensfelder Berge","lat":52.55191036,"lng":13.575879316},{"id":"13116198766","city":"Berlin","postcode":"12679","employees":"0 Beschäftigte","branch":"Sachverständige a. n. g.","top_branch":"Sonstige wissenschaftliche und technische Tätigkeiten","type":"im Handelsregister eingetragen","age":"2","planungsraum":"Ahrensfelder Berge","lat":52.548066988,"lng":13.57303407},{"id":"1326548471828","city":"Berlin","postcode":"12679","employees":"0 Beschäftigte","branch":"Einzelhandel mit Waren verschiedener Art, Hauptrichtung Nicht-Nahrungsmittel","top_branch":"Einzelhandel","type":"im Handelsregister eingetragen","age":"1","planungsraum":"Ahrensfelder Berge","lat":52.549972208,"lng":13.575261441},{"id":"132142627754","city":"Berlin","postcode":"12679","employees":"0 Beschäftigte","branch":"Herstellung von Fantasieschmuck","top_branch":"Herstellung von sonstigen Waren","type":"im Handelsregister eingetragen","age":"1","planungsraum":"Ahrensfelder Berge","lat":52.554653408,"lng":13.576074238},{"id":"1320470471568","city":"Berlin","postcode":"12679","employees":"0 Beschäftigte","branch":"Dienstleistung im Bereich Veranstaltungstechnik","top_branch":"Kunstschaffende Tätigkeiten und Tätigkeiten in der darstellenden Kunst","type":"im Handelsregister eingetragen","age":"1","planungsraum":"Ahrensfelder Berge","lat":52.549358,"lng":13.581244192},{"id":"131763187106","city":"Berlin","postcode":"12679","employees":"0 Beschäftigte","branch":"Sonstige soziale Beratungsdienste","top_branch":"Sozialwesen, ohne Heime","type":"im Handelsregister eingetragen","age":"1","planungsraum":"Ahrensfelder Berge","lat":52.553334841,"lng":13.57780508},{"id":"132434227474","city":"Berlin","postcode":"12679","employees":"0 Beschäftigte","branch":"Einzelhandel mit Haushaltsgegenständen a. n. g.","top_branch":"Einzelhandel","type":"im Handelsregister eingetragen","age":"1","planungsraum":"Ahrensfelder Berge","lat":52.550135043,"lng":13.584306484},{"id":"1305455471518","city":"Berlin","postcode":"12679","employees":"7 - 9 Beschäftigte","branch":"Restaurants mit Bedienung","top_branch":"Gastronomie","type":"im Handelsregister eingetragen","age":"2","planungsraum":"Ahrensfelder Berge","lat":52.550743733,"lng":13.578665591},{"id":"133095367512","city":"Berlin","postcode":"12679","employees":"1 - 3 Beschäftigte","branch":"Reparatur und Instandhaltung von Uhren und Schmuck","top_branch":"Reparatur und Instandhaltung von Datenverarbeitungsgeräten und Gebrauchsgütern sowie von Kraftwagen und Krafträdern","type":"Kleingewerbetreibender","age":"1","planungsraum":"Ahrensfelder Berge","lat":52.551218561,"lng":13.576295369},{"id":"133391827394","city":"Berlin","postcode":"12679","employees":"0 Beschäftigte","branch":"Bedrucken von Textilien als Sofortservice","top_branch":"Einzelhandel","type":"im Handelsregister eingetragen","age":"1","planungsraum":"Ahrensfelder Berge","lat":52.550515712,"lng":13.575888619},{"id":"1293982871276","city":"Berlin","postcode":"12679","employees":"0 Beschäftigte","branch":"Herstellung von Vlogs","top_branch":"Herstellung, Verleih und Vertrieb von Filmen und Fernsehprogrammen, Kinos, Tonstudios und Verlegen von Musik","type":"im Handelsregister eingetragen","age":"2","planungsraum":"Ahrensfelder Berge","lat":52.549901882,"lng":13.57587872},{"id":"132008467282","city":"Berlin","postcode":"12679","employees":"0 Beschäftigte","branch":"Einzelhandel mit Waren verschiedener Art, Hauptrichtung Nicht-Nahrungsmittel","top_branch":"Einzelhandel","type":"im Handelsregister eingetragen","age":"2","planungsraum":"Ahrensfelder Berge","lat":52.54991036,"lng":13.579204979},{"id":"132007447248","city":"Berlin","postcode":"12679","employees":"0 Beschäftigte","branch":"Onlinemarketing","top_branch":"Werbung und Marktforschung sowie Public-Relations-Beratung","type":"im Handelsregister eingetragen","age":"1","planungsraum":"Ahrensfelder Berge","lat":52.553095286,"lng":13.579603532},{"id":"133342327744","city":"Berlin","postcode":"12679","employees":"0 Beschäftigte","branch":"Akustik- und Trockenbau","top_branch":"Vorbereitende Baustellenarbeiten, Bauinstallation und sonstiges Ausbaugewerbe","type":"im Handelsregister eingetragen","age":"1","planungsraum":"Ahrensfelder Berge","lat":52.550563389,"lng":13.579876061},{"id":"1312723271744","city":"Berlin","postcode":"12679","employees":"0 Beschäftigte","branch":"Herstellung von sonstigen Videofilmen, von Filmen und Fernsehprogrammen","top_branch":"Herstellung, Verleih und Vertrieb von Filmen und Fernsehprogrammen, Kinos, Tonstudios und Verlegen von Musik","type":"Kleingewerbetreibender","age":"2","planungsraum":"Ahrensfelder Berge","lat":52.549358,"lng":13.581244192},{"id":"132988387946","city":"Berlin","postcode":"12679","employees":"0 Beschäftigte","branch":"Herstellung von Vlogs","top_branch":"Herstellung, Verleih und Vertrieb von Filmen und Fernsehprogrammen, Kinos, Tonstudios und Verlegen von Musik","type":"im Handelsregister eingetragen","age":"1","planungsraum":"Ahrensfelder Berge","lat":52.550328176,"lng":13.583363595},{"id":"132442987766","city":"Berlin","postcode":"12679","employees":"0 Beschäftigte","branch":"Akustik- und Trockenbau","top_branch":"Vorbereitende Baustellenarbeiten, Bauinstallation und sonstiges Ausbaugewerbe","type":"im Handelsregister eingetragen","age":"1","planungsraum":"Ahrensfelder Berge","lat":52.550563389,"lng":13.579876061},{"id":"1312648871496","city":"Berlin","postcode":"12679","employees":"0 Beschäftigte","branch":"Abbrucharbeiten","top_branch":"Vorbereitende Baustellenarbeiten, Bauinstallation und sonstiges Ausbaugewerbe","type":"im Handelsregister eingetragen","age":"2","planungsraum":"Ahrensfelder Berge","lat":52.552225852,"lng":13.579198757},{"id":"133515007500","city":"Berlin","postcode":"12679","employees":"0 Beschäftigte","branch":"Einzelhandel mit Nahrungs- und Genussmitteln und Getränken, ohne ausgeprägten Schwerpunkt","top_branch":"Einzelhandel","type":"im Handelsregister eingetragen","age":"1","planungsraum":"Ahrensfelder Berge","lat":52.550743733,"lng":13.578665591},{"id":"1368483071610","city":"Berlin","postcode":"12679","employees":"0 Beschäftigte","branch":"Entwicklung und Programmierung von Internetpräsentationen","top_branch":"Erbringung von Dienstleistungen der Informationstechnologie","type":"im Handelsregister eingetragen","age":"0","planungsraum":"Ahrensfelder Berge","lat":52.548073198,"lng":13.576587218},{"id":"1364356271854","city":"Berlin","postcode":"12679","employees":"0 Beschäftigte","branch":"Akustik- und Trockenbau","top_branch":"Vorbereitende Baustellenarbeiten, Bauinstallation und sonstiges Ausbaugewerbe","type":"im Handelsregister eingetragen","age":"1","planungsraum":"Ahrensfelder Berge","lat":52.553892621,"lng":13.575138075},{"id":"133703347778","city":"Berlin","postcode":"12679","employees":"0 Beschäftigte","branch":"Tiertrainer, Abrichten von Tieren","top_branch":"Erbringung von überwiegend persönlichen Dienstleistungen","type":"im Handelsregister eingetragen","age":"1","planungsraum":"Ahrensfelder Berge","lat":52.549643651,"lng":13.579117277},{"id":"137771407380","city":"Berlin","postcode":"12679","employees":"0 Beschäftigte","branch":"Einzelhandel mit Waren verschiedener Art, Hauptrichtung Nicht-Nahrungsmittel","top_branch":"Einzelhandel","type":"im Handelsregister eingetragen","age":"0","planungsraum":"Ahrensfelder Berge","lat":52.551264599,"lng":13.579698359},{"id":"1372743671812","city":"Berlin","postcode":"12679","employees":"0 Beschäftigte","branch":"Garten- und Landschaftsbau","top_branch":"Gebäudebetreuung, Garten- und Landschaftsbau","type":"im Handelsregister eingetragen","age":"0","planungsraum":"Ahrensfelder Berge","lat":52.549125838,"lng":13.580916014},{"id":"136523767792","city":"Berlin","postcode":"12679","employees":"0 Beschäftigte","branch":"Einzelhandel mit Waren verschiedener Art, Hauptrichtung Nicht-Nahrungsmittel","top_branch":"Einzelhandel","type":"im Handelsregister eingetragen","age":"1","planungsraum":"Ahrensfelder Berge","lat":52.554145151,"lng":13.577644604},{"id":"1382827871426","city":"Berlin","postcode":"12679","employees":"0 Beschäftigte","branch":"Akustik- und Trockenbau","top_branch":"Vorbereitende Baustellenarbeiten, Bauinstallation und sonstiges Ausbaugewerbe","type":"im Handelsregister eingetragen","age":"0","planungsraum":"Ahrensfelder Berge","lat":52.550328178,"lng":13.583363595},{"id":"136623547118","city":"Berlin","postcode":"12679","employees":"0 Beschäftigte","branch":"Sprachschulen","top_branch":"Erziehung und Unterricht","type":"im Handelsregister eingetragen","age":"0","planungsraum":"Ahrensfelder Berge","lat":52.548066989,"lng":13.57303407},{"id":"1358959871866","city":"Berlin","postcode":"12679","employees":"0 Beschäftigte","branch":"Montage, Installation und Aufbau von Ständen auf Märkten, Ausstellungen und Messen","top_branch":"Vorbereitende Baustellenarbeiten, Bauinstallation und sonstiges Ausbaugewerbe","type":"im Handelsregister eingetragen","age":"1","planungsraum":"Ahrensfelder Berge","lat":52.551397694,"lng":13.574904735},{"id":"138192007400","city":"Berlin","postcode":"12679","employees":"0 Beschäftigte","branch":"Herstellung von Filmwerbung","top_branch":"Herstellung, Verleih und Vertrieb von Filmen und Fernsehprogrammen, Kinos, Tonstudios und Verlegen von Musik","type":"im Handelsregister eingetragen","age":"0","planungsraum":"Ahrensfelder Berge","lat":52.550221965,"lng":13.580386693},{"id":"137049367312","city":"Berlin","postcode":"12679","employees":"0 Beschäftigte","branch":"Einzelhandel mit kosmetischen Erzeugnissen und Körperpflegemitteln","top_branch":"Einzelhandel","type":"im Handelsregister eingetragen","age":"1","planungsraum":"Ahrensfelder Berge","lat":52.552058486,"lng":13.578605901},{"id":"1375765271884","city":"Berlin","postcode":"12679","employees":"0 Beschäftigte","branch":"Einzelcoaching, Teamcoaching","top_branch":"Erziehung und Unterricht","type":"im Handelsregister eingetragen","age":"0","planungsraum":"Ahrensfelder Berge","lat":52.547443826,"lng":13.574192848},{"id":"135087127904","city":"Berlin","postcode":"12679","employees":"0 Beschäftigte","branch":"Einzelhandel mit Waren verschiedener Art, Hauptrichtung Nicht-Nahrungsmittel","top_branch":"Einzelhandel","type":"im Handelsregister eingetragen","age":"1","planungsraum":"Ahrensfelder Berge","lat":52.554234258,"lng":13.577473804},{"id":"1379922071740","city":"Berlin","postcode":"12679","employees":"0 Beschäftigte","branch":"Verwaltung von eigenen Grundstücken, Gebäuden, Wohnungen","top_branch":"Grundstücks- und Wohnungswesen","type":"Kleingewerbetreibender","age":"1","planungsraum":"Ahrensfelder Berge","lat":52.551910362,"lng":13.575879317},{"id":"135486847228","city":"Berlin","postcode":"12679","employees":"0 Beschäftigte","branch":"Onlinemarketing","top_branch":"Werbung und Marktforschung sowie Public-Relations-Beratung","type":"im Handelsregister eingetragen","age":"1","planungsraum":"Ahrensfelder Berge","lat":52.54864698,"lng":13.573224074},{"id":"137947267242","city":"Berlin","postcode":"12679","employees":"0 Beschäftigte","branch":"Direktmarketing","top_branch":"Werbung und Marktforschung sowie Public-Relations-Beratung","type":"im Handelsregister eingetragen","age":"47","planungsraum":"Ahrensfelder Berge","lat":52.553892621,"lng":13.575138075},{"id":"135443467782","city":"Berlin","postcode":"12679","employees":"0 Beschäftigte","branch":"Onlinemarketing","top_branch":"Werbung und Marktforschung sowie Public-Relations-Beratung","type":"im Handelsregister eingetragen","age":"1","planungsraum":"Ahrensfelder Berge","lat":52.552897078,"lng":13.579986529},{"id":"137787907930","city":"Berlin","postcode":"12679","employees":"0 Beschäftigte","branch":"Sonstiges Sozialwesen a. n. g. (ohne Jugendarbeit und soziale Beratungsdienste)","top_branch":"Sozialwesen, ohne Heime","type":"im Handelsregister eingetragen","age":"1","planungsraum":"Ahrensfelder Berge","lat":52.550896941,"lng":13.581116267},{"id":"1362968471228","city":"Berlin","postcode":"12679","employees":"0 Beschäftigte","branch":"Überführung von einzelnen Kraftfahrzeugen","top_branch":"Lagerei sowie Erbringung von sonstigen Dienstleistungen für den Verkehr","type":"im Handelsregister eingetragen","age":"1","planungsraum":"Ahrensfelder Berge","lat":52.552518027,"lng":13.577365572},{"id":"136147927264","city":"Berlin","postcode":"12679","employees":"0 Beschäftigte","branch":"Bauhilfsdienstleistungen","top_branch":"Vorbereitende Baustellenarbeiten, Bauinstallation und sonstiges Ausbaugewerbe","type":"im Handelsregister eingetragen","age":"1","planungsraum":"Ahrensfelder Berge","lat":52.553503827,"lng":13.576726549},{"id":"1344427271424","city":"Berlin","postcode":"12679","employees":"0 Beschäftigte","branch":"Tiertrainer, Abrichten von Tieren","top_branch":"Erbringung von überwiegend persönlichen Dienstleistungen","type":"im Handelsregister eingetragen","age":"1","planungsraum":"Ahrensfelder Berge","lat":52.553892619,"lng":13.575138074},{"id":"1363690271634","city":"Berlin","postcode":"12679","employees":"0 Beschäftigte","branch":"Direktmarketing","top_branch":"Werbung und Marktforschung sowie Public-Relations-Beratung","type":"im Handelsregister eingetragen","age":"5","planungsraum":"Ahrensfelder Berge","lat":52.552838827,"lng":13.574836774},{"id":"136756747558","city":"Berlin","postcode":"12679","employees":"0 Beschäftigte","branch":"Mietwagen mit Fahrer auf Abruf","top_branch":"Landverkehr und Transport in Rohrfernleitungen","type":"im Handelsregister eingetragen","age":"0","planungsraum":"Ahrensfelder Berge","lat":52.550358422,"lng":13.581448122},{"id":"135741967732","city":"Berlin","postcode":"12679","employees":"0 Beschäftigte","branch":"Vermietung von sonstigen Gebrauchsgütern","top_branch":"Vermietung und Leasing","type":"im Handelsregister eingetragen","age":"1","planungsraum":"Ahrensfelder Berge","lat":52.554520398,"lng":13.575387485},{"id":"1378043471478","city":"Berlin","postcode":"12679","employees":"0 Beschäftigte","branch":"Durchführung von Veranstaltungen, Veranstaltungsservice","top_branch":"Erbringung von Dienstleistungen des Sports, der Unterhaltung und der Erholung","type":"im Handelsregister eingetragen","age":"0","planungsraum":"Ahrensfelder Berge","lat":52.547443826,"lng":13.574192848},{"id":"138566167872","city":"Berlin","postcode":"12679","employees":"0 Beschäftigte","branch":"Verlegen von Büchern","top_branch":"Verlagswesen","type":"im Handelsregister eingetragen","age":"0","planungsraum":"Ahrensfelder Berge","lat":52.552915142,"lng":13.578176574},{"id":"135426367212","city":"Berlin","postcode":"12679","employees":"0 Beschäftigte","branch":"Kurierdienste","top_branch":"Post-, Kurier- und Expressdienste","type":"im Handelsregister eingetragen","age":"1","planungsraum":"Ahrensfelder Berge","lat":52.549125838,"lng":13.580916014},{"id":"1367772671242","city":"Berlin","postcode":"12679","employees":"0 Beschäftigte","branch":"Erbringung von sonstigen Dienstleistungen für kunstschaffende Tätigkeiten und darstellende Künste a. n. g.","top_branch":"Kunstschaffende Tätigkeiten und Tätigkeiten in der darstellenden Kunst","type":"im Handelsregister eingetragen","age":"1","planungsraum":"Ahrensfelder Berge","lat":52.551347261,"lng":13.57532531},{"id":"1383427871426","city":"Berlin","postcode":"12679","employees":"0 Beschäftigte","branch":"Vermittlung von Bausparverträgen","top_branch":"Mit Finanz- und Versicherungsdienstleistungen verbundene Tätigkeiten","type":"im Handelsregister eingetragen","age":"0","planungsraum":"Ahrensfelder Berge","lat":52.551997909,"lng":13.575221604},{"id":"135259747658","city":"Berlin","postcode":"12679","employees":"0 Beschäftigte","branch":"Onlinemarketing","top_branch":"Werbung und Marktforschung sowie Public-Relations-Beratung","type":"im Handelsregister eingetragen","age":"1","planungsraum":"Ahrensfelder Berge","lat":52.553551739,"lng":13.575388961},{"id":"1383440471468","city":"Berlin","postcode":"12679","employees":"0 Beschäftigte","branch":"Einzelhandel mit Waren verschiedener Art, Hauptrichtung Nicht-Nahrungsmittel","top_branch":"Einzelhandel","type":"im Handelsregister eingetragen","age":"0","planungsraum":"Ahrensfelder Berge","lat":52.550576223,"lng":13.579716585},{"id":"137770327344","city":"Berlin","postcode":"12679","employees":"0 Beschäftigte","branch":"Einzelhandel mit Waren verschiedener Art, Hauptrichtung Nicht-Nahrungsmittel","top_branch":"Einzelhandel","type":"im Handelsregister eingetragen","age":"0","planungsraum":"Ahrensfelder Berge","lat":52.550074329,"lng":13.574560742},{"id":"1403365871886","city":"Berlin","postcode":"12679","employees":"0 Beschäftigte","branch":"Einzelhandel mit Waren verschiedener Art, Hauptrichtung Nicht-Nahrungsmittel","top_branch":"Einzelhandel","type":"im Handelsregister eingetragen","age":"0","planungsraum":"Ahrensfelder Berge","lat":52.548859079,"lng":13.578468577},{"id":"1394265071550","city":"Berlin","postcode":"12679","employees":"0 Beschäftigte","branch":"hauswirtschaftliche Versorgung, Haushaltshilfe","top_branch":"Sozialwesen, ohne Heime","type":"im Handelsregister eingetragen","age":"0","planungsraum":"Ahrensfelder Berge","lat":52.549941238,"lng":13.575531942},{"id":"139761787726","city":"Berlin","postcode":"12679","employees":"0 Beschäftigte","branch":"Programmierungstätigkeiten","top_branch":"Erbringung von Dienstleistungen der Informationstechnologie","type":"im Handelsregister eingetragen","age":"0","planungsraum":"Ahrensfelder Berge","lat":52.554489868,"lng":13.577009204},{"id":"139863307110","city":"Berlin","postcode":"12679","employees":"0 Beschäftigte","branch":"Additive Fertigung, 3D Druck","top_branch":"Herstellung von sonstigen Waren","type":"im Handelsregister eingetragen","age":"0","planungsraum":"Ahrensfelder Berge","lat":52.551910363,"lng":13.575879317},{"id":"1403930471768","city":"Berlin","postcode":"12679","employees":"0 Beschäftigte","branch":"Erbringung von Beratungsleistungen auf dem Gebiet der Informationstechnologie","top_branch":"Erbringung von Dienstleistungen der Informationstechnologie","type":"im Handelsregister eingetragen","age":"0","planungsraum":"Ahrensfelder Berge","lat":52.554329813,"lng":13.577317951},{"id":"140344507150","city":"Berlin","postcode":"12679","employees":"0 Beschäftigte","branch":"Betrieb von Spielautomaten","top_branch":"Spiel-, Wett- und Lotteriewesen","type":"im Handelsregister eingetragen","age":"0","planungsraum":"Ahrensfelder Berge","lat":52.551723497,"lng":13.580924387},{"id":"14022282794","city":"Berlin","postcode":"12679","employees":"0 Beschäftigte","branch":"Einzelhandel mit Waren verschiedener Art, Hauptrichtung Nicht-Nahrungsmittel","top_branch":"Einzelhandel","type":"im Handelsregister eingetragen","age":"0","planungsraum":"Ahrensfelder Berge","lat":52.554234258,"lng":13.577473805},{"id":"1402775471918","city":"Berlin","postcode":"12679","employees":"0 Beschäftigte","branch":"Direktmarketing","top_branch":"Werbung und Marktforschung sowie Public-Relations-Beratung","type":"im Handelsregister eingetragen","age":"0","planungsraum":"Ahrensfelder Berge","lat":52.551910361,"lng":13.575879317},{"id":"139747447248","city":"Berlin","postcode":"12679","employees":"0 Beschäftigte","branch":"Einzelhandel mit Waren verschiedener Art, Hauptrichtung Nicht-Nahrungsmittel","top_branch":"Einzelhandel","type":"im Handelsregister eingetragen","age":"0","planungsraum":"Ahrensfelder Berge","lat":52.553109365,"lng":13.57540355},{"id":"140523547118","city":"Berlin","postcode":"12679","employees":"0 Beschäftigte","branch":"Erbringung von allen anderen überwiegend persönlichen Dienstleistungen a. n. g.","top_branch":"Erbringung von überwiegend persönlichen Dienstleistungen","type":"im Handelsregister eingetragen","age":"0","planungsraum":"Ahrensfelder Berge","lat":52.550382641,"lng":13.579383868},{"id":"1390115471718","city":"Berlin","postcode":"12679","employees":"0 Beschäftigte","branch":"Überführung von einzelnen Kraftfahrzeugen","top_branch":"Lagerei sowie Erbringung von sonstigen Dienstleistungen für den Verkehr","type":"im Handelsregister eingetragen","age":"0","planungsraum":"Ahrensfelder Berge","lat":52.550629254,"lng":13.57500975},{"id":"140054167472","city":"Berlin","postcode":"12679","employees":"0 Beschäftigte","branch":"Programmierungstätigkeiten","top_branch":"Erbringung von Dienstleistungen der Informationstechnologie","type":"im Handelsregister eingetragen","age":"0","planungsraum":"Ahrensfelder Berge","lat":52.554489868,"lng":13.577009204},{"id":"1391257271524","city":"Berlin","postcode":"12679","employees":"0 Beschäftigte","branch":"Akustik- und Trockenbau","top_branch":"Vorbereitende Baustellenarbeiten, Bauinstallation und sonstiges Ausbaugewerbe","type":"im Handelsregister eingetragen","age":"0","planungsraum":"Ahrensfelder Berge","lat":52.554489868,"lng":13.577009204},{"id":"1397945471818","city":"Berlin","postcode":"12679","employees":"0 Beschäftigte","branch":"Kommunikationsdesign, Mediendesign","top_branch":"Sonstige wissenschaftliche und technische Tätigkeiten","type":"im Handelsregister eingetragen","age":"0","planungsraum":"Ahrensfelder Berge","lat":52.554036168,"lng":13.576555464},{"id":"1412978471928","city":"Berlin","postcode":"12679","employees":"0 Beschäftigte","branch":"noch unbekannt","top_branch":"NULL","type":"im Handelsregister eingetragen","age":"0","planungsraum":"Ahrensfelder Berge","lat":52.548434599,"lng":13.577065824},{"id":"141205987866","city":"Berlin","postcode":"12679","employees":"1 - 3 Beschäftigte","branch":"Entrümpelungsdienst","top_branch":"Erbringung von überwiegend persönlichen Dienstleistungen","type":"im Handelsregister eingetragen","age":"0","planungsraum":"Ahrensfelder Berge","lat":52.552075622,"lng":13.581646884},{"id":"1408633871446","city":"Berlin","postcode":"12679","employees":"0 Beschäftigte","branch":"Tätigkeiten von Versicherungsvertreterinnen und -vertretern","top_branch":"Mit Finanz- und Versicherungsdienstleistungen verbundene Tätigkeiten","type":"im Handelsregister eingetragen","age":"0","planungsraum":"Ahrensfelder Berge","lat":52.551471964,"lng":13.579756673}]