[{"id":"7372806912","city":"Berlin","postcode":"10365","employees":"500 - 999 Beschäftigte","branch":"Sonstige private Wach- und Sicherheitsdienste","top_branch":"Wach- und Sicherheitsdienste sowie Detekteien","type":"Kleingewerbetreibender","age":"29","planungsraum":"Bornitzstraße","lat":52.520749811,"lng":13.489582648},{"id":"102427561710","city":"Berlin","postcode":"10365","employees":"1 - 3 Beschäftigte","branch":"Beteiligungsgesellschaften","top_branch":"Erbringung von Finanzdienstleistungen","type":"Kleingewerbetreibender","age":"29","planungsraum":"Bornitzstraße","lat":52.520749811,"lng":13.489582648},{"id":"12113256530","city":"Berlin","postcode":"10365","employees":"7 - 9 Beschäftigte","branch":"Konzertveranstalter","top_branch":"Kunstschaffende Tätigkeiten und Tätigkeiten in der darstellenden Kunst","type":"Kleingewerbetreibender","age":"28","planungsraum":"Bornitzstraße","lat":52.520788473,"lng":13.490669037},{"id":"143985061940","city":"Berlin","postcode":"10365","employees":"0 Beschäftigte","branch":"Betrieb von Sportanlagen","top_branch":"Erbringung von Dienstleistungen des Sports, der Unterhaltung und der Erholung","type":"Kleingewerbetreibender","age":"27","planungsraum":"Bornitzstraße","lat":52.520533708,"lng":13.497229701},{"id":"143999561998","city":"Berlin","postcode":"10365","employees":"7 - 9 Beschäftigte","branch":"Kegelbahn, Bowlingbahn","top_branch":"Erbringung von Dienstleistungen des Sports, der Unterhaltung und der Erholung","type":"Kleingewerbetreibender","age":"27","planungsraum":"Bornitzstraße","lat":52.520533708,"lng":13.497229701},{"id":"158267061068","city":"Berlin","postcode":"10365","employees":"1 - 3 Beschäftigte","branch":"Verlagswesen","top_branch":"Verlagswesen","type":"Kleingewerbetreibender","age":"27","planungsraum":"Bornitzstraße","lat":52.521183879,"lng":13.486913122},{"id":"1605175670","city":"Berlin","postcode":"10365","employees":"0 Beschäftigte","branch":"Event-Caterer","top_branch":"Gastronomie","type":"im Handelsregister eingetragen","age":"27","planungsraum":"Bornitzstraße","lat":52.519190622,"lng":13.488381486},{"id":"161290061160","city":"Berlin","postcode":"10365","employees":"10 - 19 Beschäftigte","branch":"Durchführung von Veranstaltungen, Veranstaltungsservice","top_branch":"Erbringung von Dienstleistungen des Sports, der Unterhaltung und der Erholung","type":"Kleingewerbetreibender","age":"26","planungsraum":"Bornitzstraße","lat":52.521183879,"lng":13.486913122},{"id":"16717006680","city":"Berlin","postcode":"10365","employees":"0 Beschäftigte","branch":"Großhandel mit Sportartikeln und -zubehör","top_branch":"Großhandel","type":"im Handelsregister eingetragen","age":"26","planungsraum":"Bornitzstraße","lat":52.520533717,"lng":13.497229702},{"id":"215286061144","city":"Berlin","postcode":"10365","employees":"1 - 3 Beschäftigte","branch":"Verlegen von Büchern","top_branch":"Verlagswesen","type":"Kleingewerbetreibender","age":"25","planungsraum":"Bornitzstraße","lat":52.520788483,"lng":13.490669053},{"id":"23070806832","city":"Berlin","postcode":"10365","employees":"20 - 49 Beschäftigte","branch":"Großhandel mit Datenverarbeitungsgeräten, peripheren Geräten und Software","top_branch":"Großhandel","type":"Kleingewerbetreibender","age":"24","planungsraum":"Bornitzstraße","lat":52.521455508,"lng":13.486906028},{"id":"24808456338","city":"Berlin","postcode":"10365","employees":"0 Beschäftigte","branch":"Einzelhandel mit Hardware","top_branch":"Einzelhandel","type":"im Handelsregister eingetragen","age":"24","planungsraum":"Bornitzstraße","lat":52.51948391,"lng":13.487014068},{"id":"23812856514","city":"Berlin","postcode":"10365","employees":"200 - 499 Beschäftigte","branch":"Facility Management","top_branch":"Gebäudebetreuung, Garten- und Landschaftsbau","type":"Kleingewerbetreibender","age":"28","planungsraum":"Bornitzstraße","lat":52.520749811,"lng":13.489582648},{"id":"24270456818","city":"Berlin","postcode":"10365","employees":"10 - 19 Beschäftigte","branch":"Management, Marketingberatung (Projektmanagement)","top_branch":"Verwaltung und Führung von Unternehmen und Betrieben, Unternehmensberatung","type":"Kleingewerbetreibender","age":"24","planungsraum":"Bornitzstraße","lat":52.520788473,"lng":13.490669037},{"id":"260278061112","city":"Berlin","postcode":"10365","employees":"20 - 49 Beschäftigte","branch":"Büros baufachlicher Sachverständiger","top_branch":"Tätigkeiten von Architektur- und Ingenieurbüros, technische, physikalische und chemische Untersuchung","type":"Kleingewerbetreibender","age":"20","planungsraum":"Bornitzstraße","lat":52.520736552,"lng":13.489998009},{"id":"267000562","city":"Berlin","postcode":"10365","employees":"1 - 3 Beschäftigte","branch":"Durchführung von Veranstaltungen, Veranstaltungsservice","top_branch":"Erbringung von Dienstleistungen des Sports, der Unterhaltung und der Erholung","type":"Kleingewerbetreibender","age":"24","planungsraum":"Bornitzstraße","lat":52.520788483,"lng":13.490669053},{"id":"284753561014","city":"Berlin","postcode":"10365","employees":"0 Beschäftigte","branch":"Erbringung von sonstigen Dienstleistungen der Informationstechnologie","top_branch":"Erbringung von Dienstleistungen der Informationstechnologie","type":"im Handelsregister eingetragen","age":"23","planungsraum":"Bornitzstraße","lat":52.520788473,"lng":13.490669037},{"id":"297357061428","city":"Berlin","postcode":"10365","employees":"0 Beschäftigte","branch":"Erbringung von sonstigen Dienstleistungen der Informationstechnologie","top_branch":"Erbringung von Dienstleistungen der Informationstechnologie","type":"im Handelsregister eingetragen","age":"23","planungsraum":"Bornitzstraße","lat":52.520180176,"lng":13.491805185},{"id":"314887561550","city":"Berlin","postcode":"10365","employees":"10 - 19 Beschäftigte","branch":"Unternehmensberatung","top_branch":"Verwaltung und Führung von Unternehmen und Betrieben, Unternehmensberatung","type":"Kleingewerbetreibender","age":"22","planungsraum":"Bornitzstraße","lat":52.520788481,"lng":13.490669053},{"id":"317858561434","city":"Berlin","postcode":"10365","employees":"1 - 3 Beschäftigte","branch":"Management, Marketingberatung (Projektmanagement)","top_branch":"Verwaltung und Führung von Unternehmen und Betrieben, Unternehmensberatung","type":"Kleingewerbetreibender","age":"22","planungsraum":"Bornitzstraße","lat":52.520788473,"lng":13.490669037},{"id":"321924061696","city":"Berlin","postcode":"10365","employees":"0 Beschäftigte","branch":"Restaurants mit Bedienung","top_branch":"Gastronomie","type":"im Handelsregister eingetragen","age":"22","planungsraum":"Bornitzstraße","lat":52.520450451,"lng":13.490831396},{"id":"331876061504","city":"Berlin","postcode":"10365","employees":"10 - 19 Beschäftigte","branch":"Management, Marketingberatung (Projektmanagement)","top_branch":"Verwaltung und Führung von Unternehmen und Betrieben, Unternehmensberatung","type":"Kleingewerbetreibender","age":"22","planungsraum":"Bornitzstraße","lat":52.519651548,"lng":13.498039813},{"id":"334872561490","city":"Berlin","postcode":"10365","employees":"20 - 49 Beschäftigte","branch":"Sonstige soziale Betreuung von älteren Menschen","top_branch":"Sozialwesen, ohne Heime","type":"Kleingewerbetreibender","age":"21","planungsraum":"Bornitzstraße","lat":52.520788481,"lng":13.490669053},{"id":"34918456738","city":"Berlin","postcode":"10365","employees":"0 Beschäftigte","branch":"Übersetzen","top_branch":"Sonstige wissenschaftliche und technische Tätigkeiten","type":"im Handelsregister eingetragen","age":"21","planungsraum":"Bornitzstraße","lat":52.519641982,"lng":13.487194855},{"id":"114967147238","city":"Berlin","postcode":"10365","employees":"1 - 3 Beschäftigte","branch":"Beteiligungsgesellschaften","top_branch":"Erbringung von Finanzdienstleistungen","type":"Kleingewerbetreibender","age":"7","planungsraum":"Bornitzstraße","lat":52.520788482,"lng":13.490669053},{"id":"383787561150","city":"Berlin","postcode":"10365","employees":"10 - 19 Beschäftigte","branch":"Betrieb von Sportanlagen","top_branch":"Erbringung von Dienstleistungen des Sports, der Unterhaltung und der Erholung","type":"Kleingewerbetreibender","age":"20","planungsraum":"Bornitzstraße","lat":52.519875611,"lng":13.49755823},{"id":"38410756430","city":"Berlin","postcode":"10365","employees":"0 Beschäftigte","branch":"Managementtätigkeiten von sonstigen Holdinggesellschaften","top_branch":"Verwaltung und Führung von Unternehmen und Betrieben, Unternehmensberatung","type":"Kleingewerbetreibender","age":"27","planungsraum":"Bornitzstraße","lat":52.520749811,"lng":13.489582648},{"id":"377920561682","city":"Berlin","postcode":"10365","employees":"0 Beschäftigte","branch":"Sonstiger Einzelhandel mit Waren verschiedener Art","top_branch":"Einzelhandel","type":"im Handelsregister eingetragen","age":"20","planungsraum":"Bornitzstraße","lat":52.519633899,"lng":13.498929856},{"id":"46417706708","city":"Berlin","postcode":"10365","employees":"0 Beschäftigte","branch":"Programmierungstätigkeiten a. n. g.","top_branch":"Erbringung von Dienstleistungen der Informationstechnologie","type":"im Handelsregister eingetragen","age":"18","planungsraum":"Bornitzstraße","lat":52.520402573,"lng":13.491128256},{"id":"4585230692","city":"Berlin","postcode":"10365","employees":"10 - 19 Beschäftigte","branch":"Personalberatung","top_branch":"Verwaltung und Führung von Unternehmen und Betrieben, Unternehmensberatung","type":"Kleingewerbetreibender","age":"18","planungsraum":"Bornitzstraße","lat":52.521154022,"lng":13.487603136},{"id":"490388061552","city":"Berlin","postcode":"10365","employees":"1 - 3 Beschäftigte","branch":"Verwaltung von Wohngrundstücken, Wohngebäuden und Wohnungen für Dritte","top_branch":"Grundstücks- und Wohnungswesen","type":"Kleingewerbetreibender","age":"18","planungsraum":"Bornitzstraße","lat":52.51971546,"lng":13.496730834},{"id":"487910561642","city":"Berlin","postcode":"10365","employees":"0 Beschäftigte","branch":"Großhandel mit sonstigen Ausrüstungen und Zubehör für Maschinen sowie mit technischem Bedarf","top_branch":"Großhandel","type":"Kleingewerbetreibender","age":"18","planungsraum":"Bornitzstraße","lat":52.520252067,"lng":13.495911986},{"id":"17184078726","city":"Berlin","postcode":"10365","employees":"1 - 3 Beschäftigte","branch":"Herstellung von Filmen, Videofilmen und Fernsehprogrammen","top_branch":"Herstellung, Verleih und Vertrieb von Filmen und Fernsehprogrammen, Kinos, Tonstudios und Verlegen von Musik","type":"Kleingewerbetreibender","age":"33","planungsraum":"Bornitzstraße","lat":52.521183887,"lng":13.486913138},{"id":"1807200070","city":"Berlin","postcode":"10365","employees":"1 - 3 Beschäftigte","branch":"Sonstige private Wach- und Sicherheitsdienste","top_branch":"Wach- und Sicherheitsdienste sowie Detekteien","type":"Kleingewerbetreibender","age":"33","planungsraum":"Bornitzstraße","lat":52.520749811,"lng":13.489582648},{"id":"989778071260","city":"Berlin","postcode":"10365","employees":"50 - 99 Beschäftigte","branch":"Vermittlung von Arbeitskräften","top_branch":"Vermittlung und Überlassung von Arbeitskräften","type":"Kleingewerbetreibender","age":"9","planungsraum":"Bornitzstraße","lat":52.520749811,"lng":13.489582648},{"id":"617272871576","city":"Berlin","postcode":"10365","employees":"1 - 3 Beschäftigte","branch":"Management, Marketingberatung (Projektmanagement)","top_branch":"Verwaltung und Führung von Unternehmen und Betrieben, Unternehmensberatung","type":"Kleingewerbetreibender","age":"17","planungsraum":"Bornitzstraße","lat":52.519331604,"lng":13.48876782},{"id":"625703471678","city":"Berlin","postcode":"10365","employees":"0 Beschäftigte","branch":"Management, Marketingberatung (Projektmanagement)","top_branch":"Verwaltung und Führung von Unternehmen und Betrieben, Unternehmensberatung","type":"Kleingewerbetreibender","age":"17","planungsraum":"Bornitzstraße","lat":52.520788473,"lng":13.490669037},{"id":"64993927464","city":"Berlin","postcode":"10365","employees":"10 - 19 Beschäftigte","branch":"Erbringung von sonstigen Dienstleistungen der Informationstechnologie","top_branch":"Erbringung von Dienstleistungen der Informationstechnologie","type":"Kleingewerbetreibender","age":"16","planungsraum":"Bornitzstraße","lat":52.520782218,"lng":13.487908315},{"id":"64994467482","city":"Berlin","postcode":"10365","employees":"10 - 19 Beschäftigte","branch":"Erbringung von allen anderen wirtschaftlichen Dienstleistungen für Unternehmen und Privatpersonen a. n. g.","top_branch":"Erbringung von wirtschaftlichen Dienstleistungen für Unternehmen und Privatpersonen","type":"Kleingewerbetreibender","age":"16","planungsraum":"Bornitzstraße","lat":52.520788481,"lng":13.490669053},{"id":"66611167372","city":"Berlin","postcode":"10365","employees":"1 - 3 Beschäftigte","branch":"Herstellung von Möbeln a. n. g.","top_branch":"Herstellung von Möbeln","type":"Kleingewerbetreibender","age":"16","planungsraum":"Bornitzstraße","lat":52.52041916,"lng":13.490828966},{"id":"68344567152","city":"Berlin","postcode":"10365","employees":"4 - 6 Beschäftigte","branch":"Beteiligungsgesellschaften","top_branch":"Erbringung von Finanzdienstleistungen","type":"Kleingewerbetreibender","age":"17","planungsraum":"Bornitzstraße","lat":52.520749811,"lng":13.489582648},{"id":"680736671122","city":"Berlin","postcode":"10365","employees":"1 - 3 Beschäftigte","branch":"Facility Management","top_branch":"Gebäudebetreuung, Garten- und Landschaftsbau","type":"Kleingewerbetreibender","age":"15","planungsraum":"Bornitzstraße","lat":52.520749811,"lng":13.489582648},{"id":"69315247508","city":"Berlin","postcode":"10365","employees":"20 - 49 Beschäftigte","branch":"Erbringung von allen anderen wirtschaftlichen Dienstleistungen für Unternehmen und Privatpersonen a. n. g.","top_branch":"Erbringung von wirtschaftlichen Dienstleistungen für Unternehmen und Privatpersonen","type":"Kleingewerbetreibender","age":"16","planungsraum":"Bornitzstraße","lat":52.520788473,"lng":13.490669037},{"id":"71355487516","city":"Berlin","postcode":"10365","employees":"1 - 3 Beschäftigte","branch":"Großhandel mit industriellen Textil-, Näh- und Strickmaschinen","top_branch":"Großhandel","type":"Kleingewerbetreibender","age":"15","planungsraum":"Bornitzstraße","lat":52.519769031,"lng":13.490952926},{"id":"717916871056","city":"Berlin","postcode":"10365","employees":"0 Beschäftigte","branch":"Erbringung von Beratungsleistungen auf dem Gebiet der Informationstechnologie","top_branch":"Erbringung von Dienstleistungen der Informationstechnologie","type":"im Handelsregister eingetragen","age":"15","planungsraum":"Bornitzstraße","lat":52.520078979,"lng":13.492376616},{"id":"737273471578","city":"Berlin","postcode":"10365","employees":"10 - 19 Beschäftigte","branch":"Sonstiger Einzelhandel mit Waren verschiedener Art, Hauptrichtung Nahrungs- und Genussmittel und Getränken","top_branch":"Einzelhandel","type":"Kleingewerbetreibender","age":"15","planungsraum":"Bornitzstraße","lat":52.518578329,"lng":13.497754704},{"id":"455272561090","city":"Berlin","postcode":"10365","employees":"0 Beschäftigte","branch":"Durchführung von Veranstaltungen, Veranstaltungsservice","top_branch":"Erbringung von Dienstleistungen des Sports, der Unterhaltung und der Erholung","type":"im Handelsregister eingetragen","age":"19","planungsraum":"Bornitzstraße","lat":52.52007283,"lng":13.488092347},{"id":"744438671462","city":"Berlin","postcode":"10365","employees":"4 - 6 Beschäftigte","branch":"Einzelhandel mit Nahrungs- und Genussmitteln und Getränken, ohne ausgeprägten Schwerpunkt","top_branch":"Einzelhandel","type":"Kleingewerbetreibender","age":"14","planungsraum":"Bornitzstraße","lat":52.520498477,"lng":13.486286418},{"id":"75387907930","city":"Berlin","postcode":"10365","employees":"4 - 6 Beschäftigte","branch":"Einzelhandel in eigenem Namen mit Motorenkraftstoffen, Freie Tankstellen","top_branch":"Einzelhandel","type":"im Handelsregister eingetragen","age":"14","planungsraum":"Bornitzstraße","lat":52.521386249,"lng":13.498930507},{"id":"74763907130","city":"Berlin","postcode":"10365","employees":"100 - 199 Beschäftigte","branch":"Relocation Service","top_branch":"Erbringung von wirtschaftlichen Dienstleistungen für Unternehmen und Privatpersonen","type":"Kleingewerbetreibender","age":"14","planungsraum":"Bornitzstraße","lat":52.521455517,"lng":13.486906044},{"id":"757597271324","city":"Berlin","postcode":"10365","employees":"0 Beschäftigte","branch":"Unternehmensberatung","top_branch":"Verwaltung und Führung von Unternehmen und Betrieben, Unternehmensberatung","type":"im Handelsregister eingetragen","age":"14","planungsraum":"Bornitzstraße","lat":52.520212904,"lng":13.493592913},{"id":"772168871896","city":"Berlin","postcode":"10365","employees":"0 Beschäftigte","branch":"Sonstige Verwaltung und Führung von Unternehmen und Betrieben","top_branch":"Verwaltung und Führung von Unternehmen und Betrieben, Unternehmensberatung","type":"im Handelsregister eingetragen","age":"14","planungsraum":"Bornitzstraße","lat":52.520212904,"lng":13.493592913},{"id":"786337271124","city":"Berlin","postcode":"10365","employees":"1 - 3 Beschäftigte","branch":"Unternehmensberatung","top_branch":"Verwaltung und Führung von Unternehmen und Betrieben, Unternehmensberatung","type":"Kleingewerbetreibender","age":"14","planungsraum":"Bornitzstraße","lat":52.520788473,"lng":13.490669037},{"id":"79403647788","city":"Berlin","postcode":"10365","employees":"1 - 3 Beschäftigte","branch":"Berufsbildende weiterführende Schulen","top_branch":"Erziehung und Unterricht","type":"Kleingewerbetreibender","age":"13","planungsraum":"Bornitzstraße","lat":52.521455516,"lng":13.486906044},{"id":"825501671672","city":"Berlin","postcode":"10365","employees":"0 Beschäftigte","branch":"Sonstige Ingenieurbüros","top_branch":"Tätigkeiten von Architektur- und Ingenieurbüros, technische, physikalische und chemische Untersuchung","type":"Kleingewerbetreibender","age":"15","planungsraum":"Bornitzstraße","lat":52.520788481,"lng":13.490669053},{"id":"824877671592","city":"Berlin","postcode":"10365","employees":"1 - 3 Beschäftigte","branch":"Direktmarketing","top_branch":"Werbung und Marktforschung sowie Public-Relations-Beratung","type":"Kleingewerbetreibender","age":"12","planungsraum":"Bornitzstraße","lat":52.519239067,"lng":13.488738015},{"id":"826104671682","city":"Berlin","postcode":"10365","employees":"20 - 49 Beschäftigte","branch":"Technische, physikalische und chemische Untersuchung","top_branch":"Tätigkeiten von Architektur- und Ingenieurbüros, technische, physikalische und chemische Untersuchung","type":"Kleingewerbetreibender","age":"12","planungsraum":"Bornitzstraße","lat":52.520788481,"lng":13.490669053},{"id":"833948471828","city":"Berlin","postcode":"10365","employees":"7 - 9 Beschäftigte","branch":"Programmierungstätigkeiten a. n. g.","top_branch":"Erbringung von Dienstleistungen der Informationstechnologie","type":"Kleingewerbetreibender","age":"16","planungsraum":"Bornitzstraße","lat":52.520788481,"lng":13.490669053},{"id":"83723287776","city":"Berlin","postcode":"10365","employees":"0 Beschäftigte","branch":"Verrechnungsstellen, Abrechnungsstellen","top_branch":"Erbringung von wirtschaftlichen Dienstleistungen für Unternehmen und Privatpersonen","type":"Kleingewerbetreibender","age":"13","planungsraum":"Bornitzstraße","lat":52.520788473,"lng":13.490669037},{"id":"842853671512","city":"Berlin","postcode":"10365","employees":"0 Beschäftigte","branch":"Hausmeisterdienste","top_branch":"Gebäudebetreuung, Garten- und Landschaftsbau","type":"im Handelsregister eingetragen","age":"12","planungsraum":"Bornitzstraße","lat":52.519213902,"lng":13.49786082},{"id":"846591071970","city":"Berlin","postcode":"10365","employees":"0 Beschäftigte","branch":"Erbringung von allen anderen wirtschaftlichen Dienstleistungen für Unternehmen und Privatpersonen a. n. g.","top_branch":"Erbringung von wirtschaftlichen Dienstleistungen für Unternehmen und Privatpersonen","type":"im Handelsregister eingetragen","age":"12","planungsraum":"Bornitzstraße","lat":52.52009262,"lng":13.487278281},{"id":"871072871576","city":"Berlin","postcode":"10365","employees":"1 - 3 Beschäftigte","branch":"Kauf und Verkauf von eigenen Grundstücken, Gebäuden und Wohnungen","top_branch":"Grundstücks- und Wohnungswesen","type":"Kleingewerbetreibender","age":"11","planungsraum":"Bornitzstraße","lat":52.520443437,"lng":13.489513416},{"id":"94276507550","city":"Berlin","postcode":"10365","employees":"0 Beschäftigte","branch":"Herstellung von Datenverarbeitungsgeräten und peripheren Geräten","top_branch":"Herstellung von Datenverarbeitungsgeräten, elektronischen und optischen Erzeugnissen","type":"Kleingewerbetreibender","age":"10","planungsraum":"Bornitzstraße","lat":52.520468616,"lng":13.490139154},{"id":"877513871046","city":"Berlin","postcode":"10365","employees":"1 - 3 Beschäftigte","branch":"Beteiligungsgesellschaften","top_branch":"Erbringung von Finanzdienstleistungen","type":"Kleingewerbetreibender","age":"12","planungsraum":"Bornitzstraße","lat":52.520443437,"lng":13.489513416},{"id":"872219471398","city":"Berlin","postcode":"10365","employees":"1 - 3 Beschäftigte","branch":"Beteiligungsgesellschaften","top_branch":"Erbringung von Finanzdienstleistungen","type":"Kleingewerbetreibender","age":"11","planungsraum":"Bornitzstraße","lat":52.520788481,"lng":13.490669053},{"id":"88266607220","city":"Berlin","postcode":"10365","employees":"0 Beschäftigte","branch":"Onlinemarketing","top_branch":"Werbung und Marktforschung sowie Public-Relations-Beratung","type":"im Handelsregister eingetragen","age":"11","planungsraum":"Bornitzstraße","lat":52.520403391,"lng":13.49162827},{"id":"88768327944","city":"Berlin","postcode":"10365","employees":"7 - 9 Beschäftigte","branch":"Einzelhandel mit Back- und Süßwaren","top_branch":"Einzelhandel","type":"Kleingewerbetreibender","age":"11","planungsraum":"Bornitzstraße","lat":52.518433561,"lng":13.499042495},{"id":"8976204768","city":"Berlin","postcode":"10365","employees":"0 Beschäftigte","branch":"Verwaltung eigenen Vermögens","top_branch":"Erbringung von Finanzdienstleistungen","type":"Kleingewerbetreibender","age":"13","planungsraum":"Bornitzstraße","lat":52.520443437,"lng":13.489513416},{"id":"900363071210","city":"Berlin","postcode":"10365","employees":"20 - 49 Beschäftigte","branch":"Erbringung von allen anderen Dienstleistungen der Unterhaltung und der Erholung a. n. g.","top_branch":"Erbringung von Dienstleistungen des Sports, der Unterhaltung und der Erholung","type":"Kleingewerbetreibender","age":"11","planungsraum":"Bornitzstraße","lat":52.52095516,"lng":13.486741388},{"id":"89727787926","city":"Berlin","postcode":"10365","employees":"0 Beschäftigte","branch":"Abbrucharbeiten","top_branch":"Vorbereitende Baustellenarbeiten, Bauinstallation und sonstiges Ausbaugewerbe","type":"im Handelsregister eingetragen","age":"11","planungsraum":"Bornitzstraße","lat":52.519196194,"lng":13.498262287},{"id":"92413087436","city":"Berlin","postcode":"10365","employees":"0 Beschäftigte","branch":"Akustik- und Trockenbau","top_branch":"Vorbereitende Baustellenarbeiten, Bauinstallation und sonstiges Ausbaugewerbe","type":"im Handelsregister eingetragen","age":"10","planungsraum":"Bornitzstraße","lat":52.519242864,"lng":13.496623294},{"id":"926742071140","city":"Berlin","postcode":"10365","employees":"0 Beschäftigte","branch":"Tätigkeiten der Großhandelsvermittlung von sonstigen Waren a. n. g.","top_branch":"Großhandel","type":"im Handelsregister eingetragen","age":"10","planungsraum":"Bornitzstraße","lat":52.520448486,"lng":13.490940801},{"id":"929844671482","city":"Berlin","postcode":"10365","employees":"0 Beschäftigte","branch":"Akustik- und Trockenbau","top_branch":"Vorbereitende Baustellenarbeiten, Bauinstallation und sonstiges Ausbaugewerbe","type":"im Handelsregister eingetragen","age":"10","planungsraum":"Bornitzstraße","lat":52.519223618,"lng":13.497444537},{"id":"928617071390","city":"Berlin","postcode":"10365","employees":"0 Beschäftigte","branch":"Akustik- und Trockenbau","top_branch":"Vorbereitende Baustellenarbeiten, Bauinstallation und sonstiges Ausbaugewerbe","type":"im Handelsregister eingetragen","age":"10","planungsraum":"Bornitzstraße","lat":52.519242864,"lng":13.496623294},{"id":"94263607120","city":"Berlin","postcode":"10365","employees":"0 Beschäftigte","branch":"Tätigkeiten von Versicherungsvertreterinnen und -vertretern","top_branch":"Mit Finanz- und Versicherungsdienstleistungen verbundene Tätigkeiten","type":"im Handelsregister eingetragen","age":"10","planungsraum":"Bornitzstraße","lat":52.519399004,"lng":13.488285256},{"id":"943619471398","city":"Berlin","postcode":"10365","employees":"0 Beschäftigte","branch":"Befristete Überlassung von Arbeitskräften","top_branch":"Vermittlung und Überlassung von Arbeitskräften","type":"Kleingewerbetreibender","age":"10","planungsraum":"Bornitzstraße","lat":52.520788473,"lng":13.490669037},{"id":"9492276792","city":"Berlin","postcode":"10365","employees":"7 - 9 Beschäftigte","branch":"Einzelhandel mit Telekommunikationsgeräten","top_branch":"Einzelhandel","type":"Kleingewerbetreibender","age":"10","planungsraum":"Bornitzstraße","lat":52.521183887,"lng":13.486913138},{"id":"95068447948","city":"Berlin","postcode":"10365","employees":"0 Beschäftigte","branch":"Einzelhandel mit Kraftwagen mit einem zulässigen Gesamtgewicht von 3,5 t oder weniger","top_branch":"Einzelhandel","type":"Kleingewerbetreibender","age":"10","planungsraum":"Bornitzstraße","lat":52.519213902,"lng":13.49786082},{"id":"969413471378","city":"Berlin","postcode":"10365","employees":"10 - 19 Beschäftigte","branch":"Erbringung von sonstigen Dienstleistungen der Informationstechnologie","top_branch":"Erbringung von Dienstleistungen der Informationstechnologie","type":"Kleingewerbetreibender","age":"33","planungsraum":"Bornitzstraße","lat":52.520788481,"lng":13.490669053},{"id":"96928567952","city":"Berlin","postcode":"10365","employees":"0 Beschäftigte","branch":"Abbrucharbeiten","top_branch":"Vorbereitende Baustellenarbeiten, Bauinstallation und sonstiges Ausbaugewerbe","type":"im Handelsregister eingetragen","age":"9","planungsraum":"Bornitzstraße","lat":52.519194673,"lng":13.498685397},{"id":"97743727124","city":"Berlin","postcode":"10365","employees":"20 - 49 Beschäftigte","branch":"Ingenieurbüro für Maschinenbau, Anlagentechnik","top_branch":"Tätigkeiten von Architektur- und Ingenieurbüros, technische, physikalische und chemische Untersuchung","type":"Kleingewerbetreibender","age":"9","planungsraum":"Bornitzstraße","lat":52.520788481,"lng":13.490669053},{"id":"97588687956","city":"Berlin","postcode":"10365","employees":"0 Beschäftigte","branch":"Abbrucharbeiten","top_branch":"Vorbereitende Baustellenarbeiten, Bauinstallation und sonstiges Ausbaugewerbe","type":"im Handelsregister eingetragen","age":"9","planungsraum":"Bornitzstraße","lat":52.519194673,"lng":13.498685397},{"id":"97588807960","city":"Berlin","postcode":"10365","employees":"0 Beschäftigte","branch":"Abbrucharbeiten","top_branch":"Vorbereitende Baustellenarbeiten, Bauinstallation und sonstiges Ausbaugewerbe","type":"im Handelsregister eingetragen","age":"9","planungsraum":"Bornitzstraße","lat":52.519194673,"lng":13.498685397},{"id":"97588927964","city":"Berlin","postcode":"10365","employees":"0 Beschäftigte","branch":"Abbrucharbeiten","top_branch":"Vorbereitende Baustellenarbeiten, Bauinstallation und sonstiges Ausbaugewerbe","type":"im Handelsregister eingetragen","age":"9","planungsraum":"Bornitzstraße","lat":52.519194673,"lng":13.498685397},{"id":"1001951471838","city":"Berlin","postcode":"10365","employees":"20 - 49 Beschäftigte","branch":"Allgemeine Gebäudereinigung","top_branch":"Gebäudebetreuung, Garten- und Landschaftsbau","type":"Kleingewerbetreibender","age":"9","planungsraum":"Bornitzstraße","lat":52.520788482,"lng":13.490669053},{"id":"1021148471828","city":"Berlin","postcode":"10365","employees":"1 - 3 Beschäftigte","branch":"Großhandel mit Verpackungsmitteln aus Metall, Kunststoff","top_branch":"Großhandel","type":"Kleingewerbetreibender","age":"10","planungsraum":"Bornitzstraße","lat":52.520673167,"lng":13.498993921},{"id":"101478127604","city":"Berlin","postcode":"10365","employees":"1 - 3 Beschäftigte","branch":"Sonstige Forschung und Entwicklung a. n. g.","top_branch":"Forschung und Entwicklung","type":"Kleingewerbetreibender","age":"9","planungsraum":"Bornitzstraße","lat":52.520788473,"lng":13.490669037},{"id":"111201847728","city":"Berlin","postcode":"10365","employees":"1 - 3 Beschäftigte","branch":"Personalberatung","top_branch":"Verwaltung und Führung von Unternehmen und Betrieben, Unternehmensberatung","type":"Kleingewerbetreibender","age":"9","planungsraum":"Bornitzstraße","lat":52.520443437,"lng":13.489513416},{"id":"1043316671722","city":"Berlin","postcode":"10365","employees":"1 - 3 Beschäftigte","branch":"Tätigkeiten von Versicherungsvertreterinnen und -vertretern","top_branch":"Mit Finanz- und Versicherungsdienstleistungen verbundene Tätigkeiten","type":"im Handelsregister eingetragen","age":"8","planungsraum":"Bornitzstraße","lat":52.519486579,"lng":13.486932451},{"id":"1001793671312","city":"Berlin","postcode":"10365","employees":"100 - 199 Beschäftigte","branch":"Allgemeine Gebäudereinigung","top_branch":"Gebäudebetreuung, Garten- und Landschaftsbau","type":"Kleingewerbetreibender","age":"9","planungsraum":"Bornitzstraße","lat":52.520788473,"lng":13.490669037},{"id":"1016751671172","city":"Berlin","postcode":"10365","employees":"0 Beschäftigte","branch":"Sportboot- und Segelschulen","top_branch":"Erziehung und Unterricht","type":"Kleingewerbetreibender","age":"8","planungsraum":"Bornitzstraße","lat":52.520788473,"lng":13.490669037},{"id":"1018005071350","city":"Berlin","postcode":"10365","employees":"1 - 3 Beschäftigte","branch":"Vermittlung von Grundstücken, Gebäuden und Wohnungen für Dritte","top_branch":"Grundstücks- und Wohnungswesen","type":"Kleingewerbetreibender","age":"8","planungsraum":"Bornitzstraße","lat":52.520788482,"lng":13.490669053},{"id":"1014901871006","city":"Berlin","postcode":"10365","employees":"1 - 3 Beschäftigte","branch":"Kauf und Verkauf von eigenen Grundstücken, Gebäuden und Wohnungen","top_branch":"Grundstücks- und Wohnungswesen","type":"Kleingewerbetreibender","age":"8","planungsraum":"Bornitzstraße","lat":52.520443437,"lng":13.489513416},{"id":"1028823071410","city":"Berlin","postcode":"10365","employees":"0 Beschäftigte","branch":"Erbringung von Beratungsleistungen auf dem Gebiet der Informationstechnologie","top_branch":"Erbringung von Dienstleistungen der Informationstechnologie","type":"Kleingewerbetreibender","age":"8","planungsraum":"Bornitzstraße","lat":52.520443437,"lng":13.489513416},{"id":"1029930071100","city":"Berlin","postcode":"10365","employees":"1 - 3 Beschäftigte","branch":"Herstellung von sonstigen Videofilmen, von Filmen und Fernsehprogrammen","top_branch":"Herstellung, Verleih und Vertrieb von Filmen und Fernsehprogrammen, Kinos, Tonstudios und Verlegen von Musik","type":"im Handelsregister eingetragen","age":"8","planungsraum":"Bornitzstraße","lat":52.51934417,"lng":13.493318164},{"id":"1015596071320","city":"Berlin","postcode":"10365","employees":"0 Beschäftigte","branch":"Call Centers","top_branch":"Erbringung von wirtschaftlichen Dienstleistungen für Unternehmen und Privatpersonen","type":"Kleingewerbetreibender","age":"9","planungsraum":"Bornitzstraße","lat":52.520788482,"lng":13.490669053},{"id":"1012149071830","city":"Berlin","postcode":"10365","employees":"0 Beschäftigte","branch":"Akustik- und Trockenbau","top_branch":"Vorbereitende Baustellenarbeiten, Bauinstallation und sonstiges Ausbaugewerbe","type":"im Handelsregister eingetragen","age":"8","planungsraum":"Bornitzstraße","lat":52.519223618,"lng":13.497444522},{"id":"1028156471188","city":"Berlin","postcode":"10365","employees":"0 Beschäftigte","branch":"hauswirtschaftliche Versorgung, Haushaltshilfe","top_branch":"Sozialwesen, ohne Heime","type":"im Handelsregister eingetragen","age":"8","planungsraum":"Bornitzstraße","lat":52.519242864,"lng":13.496623294},{"id":"106940047668","city":"Berlin","postcode":"10365","employees":"0 Beschäftigte","branch":"Beteiligungsgesellschaften","top_branch":"Erbringung von Finanzdienstleistungen","type":"Kleingewerbetreibender","age":"7","planungsraum":"Bornitzstraße","lat":52.520788473,"lng":13.490669037},{"id":"106045387846","city":"Berlin","postcode":"10365","employees":"1 - 3 Beschäftigte","branch":"Sportpromoter, Sportveranstalter","top_branch":"Erbringung von Dienstleistungen des Sports, der Unterhaltung und der Erholung","type":"Kleingewerbetreibender","age":"9","planungsraum":"Bornitzstraße","lat":52.520317065,"lng":13.493245039},{"id":"106284367812","city":"Berlin","postcode":"10365","employees":"0 Beschäftigte","branch":"Betrieb von Spielautomaten","top_branch":"Spiel-, Wett- und Lotteriewesen","type":"im Handelsregister eingetragen","age":"7","planungsraum":"Bornitzstraße","lat":52.518674839,"lng":13.48810659},{"id":"109102207740","city":"Berlin","postcode":"10365","employees":"1 - 3 Beschäftigte","branch":"Großhandel mit sonstigen Nahrungs- und Genussmitteln a. n. g.","top_branch":"Großhandel","type":"Kleingewerbetreibender","age":"7","planungsraum":"Bornitzstraße","lat":52.520443437,"lng":13.489513416},{"id":"1098331271104","city":"Berlin","postcode":"10365","employees":"0 Beschäftigte","branch":"Kantinen","top_branch":"Gastronomie","type":"Kleingewerbetreibender","age":"7","planungsraum":"Bornitzstraße","lat":52.519476607,"lng":13.492215489},{"id":"1115995871986","city":"Berlin","postcode":"10365","employees":"0 Beschäftigte","branch":"Buchführung ohne Datenverarbeitungsdienste","top_branch":"Rechts- und Steuerberatung, Wirtschaftsprüfung","type":"im Handelsregister eingetragen","age":"10","planungsraum":"Bornitzstraße","lat":52.519242864,"lng":13.496623294},{"id":"1126528271094","city":"Berlin","postcode":"10365","employees":"unbekannt","branch":"Sonstige Caterer und Erbringung sonstiger Verpflegungsdienstleistungen","top_branch":"Gastronomie","type":"im Handelsregister eingetragen","age":"7","planungsraum":"Bornitzstraße","lat":52.520533717,"lng":13.497229702},{"id":"113945227174","city":"Berlin","postcode":"10365","employees":"1 - 3 Beschäftigte","branch":"Herstellung von nichtelektrischen Haushaltsgeräten","top_branch":"Herstellung von elektrischen Ausrüstungen","type":"Kleingewerbetreibender","age":"6","planungsraum":"Bornitzstraße","lat":52.519476607,"lng":13.492215489},{"id":"110238967632","city":"Berlin","postcode":"10365","employees":"0 Beschäftigte","branch":"Management, Marketingberatung (Projektmanagement)","top_branch":"Verwaltung und Führung von Unternehmen und Betrieben, Unternehmensberatung","type":"im Handelsregister eingetragen","age":"6","planungsraum":"Bornitzstraße","lat":52.520180176,"lng":13.491805185},{"id":"1133737271124","city":"Berlin","postcode":"10365","employees":"0 Beschäftigte","branch":"Akustik- und Trockenbau","top_branch":"Vorbereitende Baustellenarbeiten, Bauinstallation und sonstiges Ausbaugewerbe","type":"im Handelsregister eingetragen","age":"6","planungsraum":"Bornitzstraße","lat":52.519233224,"lng":13.49703485},{"id":"1131935471118","city":"Berlin","postcode":"10365","employees":"0 Beschäftigte","branch":"Akustik- und Trockenbau","top_branch":"Vorbereitende Baustellenarbeiten, Bauinstallation und sonstiges Ausbaugewerbe","type":"im Handelsregister eingetragen","age":"6","planungsraum":"Bornitzstraße","lat":52.519233224,"lng":13.49703485},{"id":"1121295071650","city":"Berlin","postcode":"10365","employees":"0 Beschäftigte","branch":"Ambulante Betreuungsdienste für ältere Menschen","top_branch":"Sozialwesen, ohne Heime","type":"im Handelsregister eingetragen","age":"6","planungsraum":"Bornitzstraße","lat":52.519651556,"lng":13.498039828},{"id":"1103330471768","city":"Berlin","postcode":"10365","employees":"0 Beschäftigte","branch":"Bildende Kunst","top_branch":"Kunstschaffende Tätigkeiten und Tätigkeiten in der darstellenden Kunst","type":"im Handelsregister eingetragen","age":"6","planungsraum":"Bornitzstraße","lat":52.518799335,"lng":13.487047074},{"id":"110601907730","city":"Berlin","postcode":"10365","employees":"1 - 3 Beschäftigte","branch":"Unternehmensberatung","top_branch":"Verwaltung und Führung von Unternehmen und Betrieben, Unternehmensberatung","type":"Kleingewerbetreibender","age":"6","planungsraum":"Bornitzstraße","lat":52.519476607,"lng":13.492215489},{"id":"1103705471018","city":"Berlin","postcode":"10365","employees":"7 - 9 Beschäftigte","branch":"Restaurants mit Bedienung","top_branch":"Gastronomie","type":"im Handelsregister eingetragen","age":"7","planungsraum":"Bornitzstraße","lat":52.520955158,"lng":13.486741387},{"id":"112449247308","city":"Berlin","postcode":"10365","employees":"0 Beschäftigte","branch":"Akustik- und Trockenbau","top_branch":"Vorbereitende Baustellenarbeiten, Bauinstallation und sonstiges Ausbaugewerbe","type":"im Handelsregister eingetragen","age":"6","planungsraum":"Bornitzstraße","lat":52.519213911,"lng":13.497860835},{"id":"117369007300","city":"Berlin","postcode":"10365","employees":"1 - 3 Beschäftigte","branch":"Beteiligungsgesellschaften","top_branch":"Erbringung von Finanzdienstleistungen","type":"Kleingewerbetreibender","age":"5","planungsraum":"Bornitzstraße","lat":52.519476607,"lng":13.492215489},{"id":"1171040471468","city":"Berlin","postcode":"10365","employees":"unbekannt","branch":"Erbringung sonstiger wirtschaftlicher Dienstleistungen für Unternehmen und Privatpersonen a. n. g.","top_branch":"Erbringung von wirtschaftlichen Dienstleistungen für Unternehmen und Privatpersonen","type":"im Handelsregister eingetragen","age":"11","planungsraum":"Bornitzstraße","lat":52.520180176,"lng":13.491805185},{"id":"1160724671082","city":"Berlin","postcode":"10365","employees":"0 Beschäftigte","branch":"Tätigkeiten von Versicherungsvertreterinnen und -vertretern","top_branch":"Mit Finanz- und Versicherungsdienstleistungen verbundene Tätigkeiten","type":"im Handelsregister eingetragen","age":"5","planungsraum":"Bornitzstraße","lat":52.520788481,"lng":13.490669053},{"id":"1190913671712","city":"Berlin","postcode":"10365","employees":"20 - 49 Beschäftigte","branch":"Einzelhandel mit Nahrungs- und Genussmitteln und Getränken, ohne ausgeprägten Schwerpunkt","top_branch":"Einzelhandel","type":"Kleingewerbetreibender","age":"4","planungsraum":"Bornitzstraße","lat":52.518578337,"lng":13.497754719},{"id":"1182302471008","city":"Berlin","postcode":"10365","employees":"1 - 3 Beschäftigte","branch":"Kauf und Verkauf von eigenen Wohngrundstücken, Wohngebäuden und Wohnungen","top_branch":"Grundstücks- und Wohnungswesen","type":"Kleingewerbetreibender","age":"5","planungsraum":"Bornitzstraße","lat":52.520443437,"lng":13.489513416},{"id":"1185567671892","city":"Berlin","postcode":"10365","employees":"1 - 3 Beschäftigte","branch":"Beteiligungsgesellschaften","top_branch":"Erbringung von Finanzdienstleistungen","type":"Kleingewerbetreibender","age":"5","planungsraum":"Bornitzstraße","lat":52.520788482,"lng":13.490669053},{"id":"1200408071360","city":"Berlin","postcode":"10365","employees":"1 - 3 Beschäftigte","branch":"Beteiligungsgesellschaften","top_branch":"Erbringung von Finanzdienstleistungen","type":"Kleingewerbetreibender","age":"18","planungsraum":"Bornitzstraße","lat":52.520443437,"lng":13.489513416},{"id":"116597167572","city":"Berlin","postcode":"10365","employees":"0 Beschäftigte","branch":"Tätigkeiten von Versicherungsvertreterinnen und -vertretern","top_branch":"Mit Finanz- und Versicherungsdienstleistungen verbundene Tätigkeiten","type":"im Handelsregister eingetragen","age":"5","planungsraum":"Bornitzstraße","lat":52.51944852,"lng":13.488288469},{"id":"119723887796","city":"Berlin","postcode":"10365","employees":"1 - 3 Beschäftigte","branch":"Unternehmensberatung","top_branch":"Verwaltung und Führung von Unternehmen und Betrieben, Unternehmensberatung","type":"Kleingewerbetreibender","age":"5","planungsraum":"Bornitzstraße","lat":52.518800981,"lng":13.486935074},{"id":"117323047768","city":"Berlin","postcode":"10365","employees":"1 - 3 Beschäftigte","branch":"Modedesign","top_branch":"Sonstige wissenschaftliche und technische Tätigkeiten","type":"Kleingewerbetreibender","age":"5","planungsraum":"Bornitzstraße","lat":52.519476607,"lng":13.492215489},{"id":"1191358871196","city":"Berlin","postcode":"10365","employees":"0 Beschäftigte","branch":"Herstellung von Filmwerbung","top_branch":"Herstellung, Verleih und Vertrieb von Filmen und Fernsehprogrammen, Kinos, Tonstudios und Verlegen von Musik","type":"im Handelsregister eingetragen","age":"4","planungsraum":"Bornitzstraße","lat":52.519007864,"lng":13.487044306},{"id":"116648227274","city":"Berlin","postcode":"10365","employees":"1 - 3 Beschäftigte","branch":"Sonstige Vermittlungstätigkeiten für die Erbringung von wirtschaftlichen Dienstleistungen für Unternehmen und Privatpersonen a. n. g.","top_branch":"Erbringung von wirtschaftlichen Dienstleistungen für Unternehmen und Privatpersonen","type":"Kleingewerbetreibender","age":"5","planungsraum":"Bornitzstraße","lat":52.518798447,"lng":13.487018842},{"id":"1213064471548","city":"Berlin","postcode":"10365","employees":"1 - 3 Beschäftigte","branch":"Sonstige Ingenieurbüros","top_branch":"Tätigkeiten von Architektur- und Ingenieurbüros, technische, physikalische und chemische Untersuchung","type":"Kleingewerbetreibender","age":"4","planungsraum":"Bornitzstraße","lat":52.520408741,"lng":13.491376786},{"id":"122103727124","city":"Berlin","postcode":"10365","employees":"0 Beschäftigte","branch":"Kauf und Verkauf von eigenen Wohngrundstücken, Wohngebäuden und Wohnungen","top_branch":"Grundstücks- und Wohnungswesen","type":"im Handelsregister eingetragen","age":"4","planungsraum":"Bornitzstraße","lat":52.519542324,"lng":13.492192072},{"id":"120497107570","city":"Berlin","postcode":"10365","employees":"0 Beschäftigte","branch":"Vermittlung von Wohngrundstücken, Wohngebäuden und Wohnungen für Dritte","top_branch":"Grundstücks- und Wohnungswesen","type":"im Handelsregister eingetragen","age":"4","planungsraum":"Bornitzstraße","lat":52.519834151,"lng":13.493226541},{"id":"120505087836","city":"Berlin","postcode":"10365","employees":"1 - 3 Beschäftigte","branch":"Herstellung von sonstigen Videofilmen, von Filmen und Fernsehprogrammen","top_branch":"Herstellung, Verleih und Vertrieb von Filmen und Fernsehprogrammen, Kinos, Tonstudios und Verlegen von Musik","type":"Kleingewerbetreibender","age":"4","planungsraum":"Bornitzstraße","lat":52.521183887,"lng":13.486913138},{"id":"122003047768","city":"Berlin","postcode":"10365","employees":"0 Beschäftigte","branch":"Bauträger für andere Gebäude und Bauwerke","top_branch":"Grundstücks- und Wohnungswesen","type":"Kleingewerbetreibender","age":"4","planungsraum":"Bornitzstraße","lat":52.520443437,"lng":13.489513416},{"id":"121407727924","city":"Berlin","postcode":"10365","employees":"1 - 3 Beschäftigte","branch":"Onlinemarketing","top_branch":"Werbung und Marktforschung sowie Public-Relations-Beratung","type":"Kleingewerbetreibender","age":"4","planungsraum":"Bornitzstraße","lat":52.520788481,"lng":13.490669053},{"id":"121948807960","city":"Berlin","postcode":"10365","employees":"0 Beschäftigte","branch":"Hausmeisterdienste","top_branch":"Gebäudebetreuung, Garten- und Landschaftsbau","type":"im Handelsregister eingetragen","age":"4","planungsraum":"Bornitzstraße","lat":52.519820157,"lng":13.4908925},{"id":"1215465671552","city":"Berlin","postcode":"10365","employees":"0 Beschäftigte","branch":"Verbreitung von Medieninhalten über Blogs","top_branch":"Rundfunkveranstalter, Nachrichtenagenturen und sonstige Verbreitung von Medieninhalten","type":"im Handelsregister eingetragen","age":"4","planungsraum":"Bornitzstraße","lat":52.519074257,"lng":13.493769425},{"id":"122893927464","city":"Berlin","postcode":"10365","employees":"1 - 3 Beschäftigte","branch":"Großhandel mit Textilien","top_branch":"Großhandel","type":"Kleingewerbetreibender","age":"4","planungsraum":"Bornitzstraße","lat":52.520788481,"lng":13.490669053},{"id":"123253387446","city":"Berlin","postcode":"10365","employees":"unbekannt","branch":"Einzelhandel mit Nahrungs- und Genussmitteln und Getränken, ohne ausgeprägten Schwerpunkt","top_branch":"Einzelhandel","type":"Kleingewerbetreibender","age":"16","planungsraum":"Bornitzstraße","lat":52.51843356,"lng":13.499042495},{"id":"123498907630","city":"Berlin","postcode":"10365","employees":"unbekannt","branch":"Programmierungstätigkeiten a. n. g.","top_branch":"Erbringung von Dienstleistungen der Informationstechnologie","type":"im Handelsregister eingetragen","age":"7","planungsraum":"Bornitzstraße","lat":52.519013774,"lng":13.486803935},{"id":"123919387646","city":"Berlin","postcode":"10365","employees":"1 - 3 Beschäftigte","branch":"Programmierungstätigkeiten a. n. g.","top_branch":"Erbringung von Dienstleistungen der Informationstechnologie","type":"Kleingewerbetreibender","age":"4","planungsraum":"Bornitzstraße","lat":52.518759616,"lng":13.494935017},{"id":"125360527684","city":"Berlin","postcode":"10365","employees":"0 Beschäftigte","branch":"Erbringung von allen anderen wirtschaftlichen Dienstleistungen für Unternehmen und Privatpersonen a. n. g.","top_branch":"Erbringung von wirtschaftlichen Dienstleistungen für Unternehmen und Privatpersonen","type":"Kleingewerbetreibender","age":"3","planungsraum":"Bornitzstraße","lat":52.520788481,"lng":13.490669053},{"id":"1262203871346","city":"Berlin","postcode":"10365","employees":"0 Beschäftigte","branch":"Tanzunterricht, Tanzstudios","top_branch":"Erziehung und Unterricht","type":"im Handelsregister eingetragen","age":"4","planungsraum":"Bornitzstraße","lat":52.519399004,"lng":13.488285256},{"id":"1259796671322","city":"Berlin","postcode":"10365","employees":"0 Beschäftigte","branch":"Beteiligungsgesellschaften","top_branch":"Erbringung von Finanzdienstleistungen","type":"Kleingewerbetreibender","age":"4","planungsraum":"Bornitzstraße","lat":52.520788481,"lng":13.490669053},{"id":"1286160071200","city":"Berlin","postcode":"10365","employees":"0 Beschäftigte","branch":"Beteiligungsgesellschaften","top_branch":"Erbringung von Finanzdienstleistungen","type":"Kleingewerbetreibender","age":"2","planungsraum":"Bornitzstraße","lat":52.519834151,"lng":13.493226541},{"id":"1278314471048","city":"Berlin","postcode":"10365","employees":"0 Beschäftigte","branch":"Allgemeine Gebäudereinigung","top_branch":"Gebäudebetreuung, Garten- und Landschaftsbau","type":"im Handelsregister eingetragen","age":"2","planungsraum":"Bornitzstraße","lat":52.519233224,"lng":13.49703485},{"id":"1285537871126","city":"Berlin","postcode":"10365","employees":"0 Beschäftigte","branch":"Kauf und Verkauf von eigenen Wohngrundstücken, Wohngebäuden und Wohnungen","top_branch":"Grundstücks- und Wohnungswesen","type":"Kleingewerbetreibender","age":"2","planungsraum":"Bornitzstraße","lat":52.520788481,"lng":13.490669053},{"id":"1258558871196","city":"Berlin","postcode":"10365","employees":"unbekannt","branch":"Sonstige Beherbergungsstätten","top_branch":"Beherbergung","type":"Kleingewerbetreibender","age":"3","planungsraum":"Bornitzstraße","lat":52.518578337,"lng":13.497754719},{"id":"128171707390","city":"Berlin","postcode":"10365","employees":"0 Beschäftigte","branch":"Vermietung, Verpachtung von eigenen oder geleasten Gewerbegrundstücken und Nichtwohngebäuden","top_branch":"Grundstücks- und Wohnungswesen","type":"Kleingewerbetreibender","age":"2","planungsraum":"Bornitzstraße","lat":52.520788481,"lng":13.490669053},{"id":"126743227774","city":"Berlin","postcode":"10365","employees":"0 Beschäftigte","branch":"Fußboden-, Fliesen- und Plattenlegerei, Tapeziererei","top_branch":"Vorbereitende Baustellenarbeiten, Bauinstallation und sonstiges Ausbaugewerbe","type":"Kleingewerbetreibender","age":"3","planungsraum":"Bornitzstraße","lat":52.521018881,"lng":13.495691562},{"id":"132027367912","city":"Berlin","postcode":"10365","employees":"0 Beschäftigte","branch":"EDV-Schulung, IT-Schulung","top_branch":"Erziehung und Unterricht","type":"Kleingewerbetreibender","age":"3","planungsraum":"Bornitzstraße","lat":52.521183887,"lng":13.486913138},{"id":"132366727224","city":"Berlin","postcode":"10365","employees":"0 Beschäftigte","branch":"Erbringung von Beratungsleistungen auf dem Gebiet der Informationstechnologie","top_branch":"Erbringung von Dienstleistungen der Informationstechnologie","type":"im Handelsregister eingetragen","age":"1","planungsraum":"Bornitzstraße","lat":52.520177114,"lng":13.491786804},{"id":"1312561871206","city":"Berlin","postcode":"10365","employees":"0 Beschäftigte","branch":"Beteiligungsgesellschaften","top_branch":"Erbringung von Finanzdienstleistungen","type":"Kleingewerbetreibender","age":"2","planungsraum":"Bornitzstraße","lat":52.519431537,"lng":13.486827672},{"id":"1294184471948","city":"Berlin","postcode":"10365","employees":"0 Beschäftigte","branch":"Akustik- und Trockenbau","top_branch":"Vorbereitende Baustellenarbeiten, Bauinstallation und sonstiges Ausbaugewerbe","type":"im Handelsregister eingetragen","age":"2","planungsraum":"Bornitzstraße","lat":52.520788481,"lng":13.490669053},{"id":"1303054871516","city":"Berlin","postcode":"10365","employees":"0 Beschäftigte","branch":"Sonstige mit Finanzdienstleistungen verbundene Tätigkeiten a. n. g.","top_branch":"Mit Finanz- und Versicherungsdienstleistungen verbundene Tätigkeiten","type":"im Handelsregister eingetragen","age":"2","planungsraum":"Bornitzstraße","lat":52.518675418,"lng":13.4934512},{"id":"131780347678","city":"Berlin","postcode":"10365","employees":"7 - 9 Beschäftigte","branch":"Buchführung ohne Datenverarbeitungsdienste","top_branch":"Rechts- und Steuerberatung, Wirtschaftsprüfung","type":"im Handelsregister eingetragen","age":"1","planungsraum":"Bornitzstraße","lat":52.520788481,"lng":13.490669053},{"id":"130160947698","city":"Berlin","postcode":"10365","employees":"0 Beschäftigte","branch":"Abfüllen und Verpacken","top_branch":"Erbringung von wirtschaftlichen Dienstleistungen für Unternehmen und Privatpersonen","type":"im Handelsregister eingetragen","age":"2","planungsraum":"Bornitzstraße","lat":52.519411007,"lng":13.487898305},{"id":"1295279471598","city":"Berlin","postcode":"10365","employees":"0 Beschäftigte","branch":"Einzelcoaching, Teamcoaching","top_branch":"Erziehung und Unterricht","type":"im Handelsregister eingetragen","age":"2","planungsraum":"Bornitzstraße","lat":52.520788481,"lng":13.490669053},{"id":"12960252784","city":"Berlin","postcode":"10365","employees":"0 Beschäftigte","branch":"Imbissstuben u. Ä.","top_branch":"Gastronomie","type":"Kleingewerbetreibender","age":"2","planungsraum":"Bornitzstraße","lat":52.518596811,"lng":13.494535861},{"id":"131405887196","city":"Berlin","postcode":"10365","employees":"0 Beschäftigte","branch":"Restaurants, Gaststätten, Imbissstuben, Cafés, Eissalons u. Ä.","top_branch":"Gastronomie","type":"Kleingewerbetreibender","age":"2","planungsraum":"Bornitzstraße","lat":52.519834151,"lng":13.493226541},{"id":"130402567752","city":"Berlin","postcode":"10365","employees":"unbekannt","branch":"Verwaltung von Wohngrundstücken, Wohngebäuden und Wohnungen für Dritte","top_branch":"Grundstücks- und Wohnungswesen","type":"Kleingewerbetreibender","age":"2","planungsraum":"Bornitzstraße","lat":52.520790537,"lng":13.487593456},{"id":"129928147938","city":"Berlin","postcode":"10365","employees":"0 Beschäftigte","branch":"Erbringung von sonstigen Dienstleistungen für den Verkehr a. n. g.","top_branch":"Lagerei sowie Erbringung von sonstigen Dienstleistungen für den Verkehr","type":"im Handelsregister eingetragen","age":"2","planungsraum":"Bornitzstraße","lat":52.520788481,"lng":13.490669053},{"id":"129917947598","city":"Berlin","postcode":"10365","employees":"0 Beschäftigte","branch":"Einzelcoaching, Teamcoaching","top_branch":"Erziehung und Unterricht","type":"im Handelsregister eingetragen","age":"2","planungsraum":"Bornitzstraße","lat":52.518675418,"lng":13.4934512},{"id":"132674347478","city":"Berlin","postcode":"10365","employees":"4 - 6 Beschäftigte","branch":"Event-Caterer","top_branch":"Gastronomie","type":"Kleingewerbetreibender","age":"1","planungsraum":"Bornitzstraße","lat":52.520788481,"lng":13.490669053},{"id":"132190147338","city":"Berlin","postcode":"10365","employees":"0 Beschäftigte","branch":"Verwaltung von Wohngrundstücken, Wohngebäuden und Wohnungen für Dritte","top_branch":"Grundstücks- und Wohnungswesen","type":"Kleingewerbetreibender","age":"2","planungsraum":"Bornitzstraße","lat":52.520790537,"lng":13.487593456},{"id":"129797647588","city":"Berlin","postcode":"10365","employees":"unbekannt","branch":"Kreditinstitute des Genossenschaftssektors","top_branch":"Erbringung von Finanzdienstleistungen","type":"Kleingewerbetreibender","age":"2","planungsraum":"Bornitzstraße","lat":52.520790537,"lng":13.487593456},{"id":"1336737071790","city":"Berlin","postcode":"10365","employees":"0 Beschäftigte","branch":"Beteiligungsgesellschaften","top_branch":"Erbringung von Finanzdienstleistungen","type":"Kleingewerbetreibender","age":"1","planungsraum":"Bornitzstraße","lat":52.519834151,"lng":13.493226541},{"id":"1357529471098","city":"Berlin","postcode":"10365","employees":"0 Beschäftigte","branch":"Herstellung von sonstigen Videofilmen, von Filmen und Fernsehprogrammen","top_branch":"Herstellung, Verleih und Vertrieb von Filmen und Fernsehprogrammen, Kinos, Tonstudios und Verlegen von Musik","type":"im Handelsregister eingetragen","age":"1","planungsraum":"Bornitzstraße","lat":52.519242874,"lng":13.496623295},{"id":"1338553271844","city":"Berlin","postcode":"10365","employees":"0 Beschäftigte","branch":"Speditionen","top_branch":"Lagerei sowie Erbringung von sonstigen Dienstleistungen für den Verkehr","type":"Kleingewerbetreibender","age":"2","planungsraum":"Bornitzstraße","lat":52.520788482,"lng":13.490669053},{"id":"1382179271264","city":"Berlin","postcode":"10365","employees":"0 Beschäftigte","branch":"Beteiligungsgesellschaften","top_branch":"Erbringung von Finanzdienstleistungen","type":"Kleingewerbetreibender","age":"0","planungsraum":"Bornitzstraße","lat":52.520736552,"lng":13.489998009},{"id":"135733507450","city":"Berlin","postcode":"10365","employees":"0 Beschäftigte","branch":"Desinfektion und Schädlingsbekämpfung","top_branch":"Gebäudebetreuung, Garten- und Landschaftsbau","type":"Kleingewerbetreibender","age":"1","planungsraum":"Bornitzstraße","lat":52.520736552,"lng":13.489998009},{"id":"135912607420","city":"Berlin","postcode":"10365","employees":"0 Beschäftigte","branch":"Herstellung von sonstigen Erzeugnissen a. n. g.","top_branch":"Herstellung von sonstigen Waren","type":"im Handelsregister eingetragen","age":"1","planungsraum":"Bornitzstraße","lat":52.519651557,"lng":13.498039828},{"id":"1382178671262","city":"Berlin","postcode":"10365","employees":"0 Beschäftigte","branch":"Beteiligungsgesellschaften","top_branch":"Erbringung von Finanzdienstleistungen","type":"Kleingewerbetreibender","age":"0","planungsraum":"Bornitzstraße","lat":52.520736552,"lng":13.489998009},{"id":"1339792871976","city":"Berlin","postcode":"10365","employees":"0 Beschäftigte","branch":"Beteiligungsgesellschaften","top_branch":"Erbringung von Finanzdienstleistungen","type":"Kleingewerbetreibender","age":"2","planungsraum":"Bornitzstraße","lat":52.520788481,"lng":13.490669053},{"id":"1352980271934","city":"Berlin","postcode":"10365","employees":"0 Beschäftigte","branch":"Verwaltung von Gewerbeobjekten, Gebäudemanagement","top_branch":"Grundstücks- und Wohnungswesen","type":"Kleingewerbetreibender","age":"1","planungsraum":"Bornitzstraße","lat":52.520736552,"lng":13.489998009},{"id":"134909347978","city":"Berlin","postcode":"10365","employees":"0 Beschäftigte","branch":"Programmierungstätigkeiten a. n. g.","top_branch":"Erbringung von Dienstleistungen der Informationstechnologie","type":"Kleingewerbetreibender","age":"1","planungsraum":"Bornitzstraße","lat":52.520955159,"lng":13.486741388},{"id":"1366016471388","city":"Berlin","postcode":"10365","employees":"0 Beschäftigte","branch":"Unternehmensberatung","top_branch":"Verwaltung und Führung von Unternehmen und Betrieben, Unternehmensberatung","type":"Kleingewerbetreibender","age":"1","planungsraum":"Bornitzstraße","lat":52.520736552,"lng":13.489998009},{"id":"1380541271804","city":"Berlin","postcode":"10365","employees":"unbekannt","branch":"Erbringung von allen anderen überwiegend persönlichen Dienstleistungen a. n. g.","top_branch":"Erbringung von überwiegend persönlichen Dienstleistungen","type":"im Handelsregister eingetragen","age":"4","planungsraum":"Bornitzstraße","lat":52.519834153,"lng":13.493226541},{"id":"1348673471578","city":"Berlin","postcode":"10365","employees":"unbekannt","branch":"Tätigkeiten von Versicherungsmaklerinnen und -maklern","top_branch":"Mit Finanz- und Versicherungsdienstleistungen verbundene Tätigkeiten","type":"im Handelsregister eingetragen","age":"1","planungsraum":"Bornitzstraße","lat":52.519399005,"lng":13.488285256},{"id":"1382242871476","city":"Berlin","postcode":"10365","employees":"0 Beschäftigte","branch":"Einzelhandel mit Waren verschiedener Art, Hauptrichtung Nicht-Nahrungsmittel","top_branch":"Einzelhandel","type":"im Handelsregister eingetragen","age":"0","planungsraum":"Bornitzstraße","lat":52.51957837,"lng":13.49321321},{"id":"1378732271774","city":"Berlin","postcode":"10365","employees":"0 Beschäftigte","branch":"Sonstige Instandhaltung und Reparatur von Kraftwagen mit einem zulässigen Gesamtgewicht von mehr als 3,5 t","top_branch":"Reparatur und Instandhaltung von Datenverarbeitungsgeräten und Gebrauchsgütern sowie von Kraftwagen und Krafträdern","type":"im Handelsregister eingetragen","age":"10","planungsraum":"Bornitzstraße","lat":52.521018882,"lng":13.495691562},{"id":"1358793671312","city":"Berlin","postcode":"10365","employees":"20 - 49 Beschäftigte","branch":"Erbringung von sonstigen Dienstleistungen der Informationstechnologie","top_branch":"Erbringung von Dienstleistungen der Informationstechnologie","type":"Kleingewerbetreibender","age":"1","planungsraum":"Bornitzstraße","lat":52.520788482,"lng":13.490669053},{"id":"137485147838","city":"Berlin","postcode":"10365","employees":"0 Beschäftigte","branch":"Generalunternehmung","top_branch":"Hochbau","type":"Kleingewerbetreibender","age":"0","planungsraum":"Bornitzstraße","lat":52.520788482,"lng":13.490669053},{"id":"1368928871096","city":"Berlin","postcode":"10365","employees":"0 Beschäftigte","branch":"Verwaltung eigenen Vermögens","top_branch":"Erbringung von Finanzdienstleistungen","type":"Kleingewerbetreibender","age":"1","planungsraum":"Bornitzstraße","lat":52.520788482,"lng":13.490669053},{"id":"137729347978","city":"Berlin","postcode":"10365","employees":"0 Beschäftigte","branch":"Vermietung, Verpachtung von eigenen oder geleasten Grundstücken, Gebäuden und Wohnungen","top_branch":"Grundstücks- und Wohnungswesen","type":"Kleingewerbetreibender","age":"0","planungsraum":"Bornitzstraße","lat":52.519431538,"lng":13.486827672},{"id":"1398912071040","city":"Berlin","postcode":"10365","employees":"0 Beschäftigte","branch":"Beteiligungsgesellschaften","top_branch":"Erbringung von Finanzdienstleistungen","type":"Kleingewerbetreibender","age":"16","planungsraum":"Bornitzstraße","lat":52.52044344,"lng":13.489513416},{"id":"139281607720","city":"Berlin","postcode":"10365","employees":"7 - 9 Beschäftigte","branch":"Unternehmensberatung","top_branch":"Verwaltung und Führung von Unternehmen und Betrieben, Unternehmensberatung","type":"Kleingewerbetreibender","age":"2","planungsraum":"Bornitzstraße","lat":52.520788483,"lng":13.490669053},{"id":"1399618871396","city":"Berlin","postcode":"10365","employees":"0 Beschäftigte","branch":"Unternehmensberatung","top_branch":"Verwaltung und Führung von Unternehmen und Betrieben, Unternehmensberatung","type":"im Handelsregister eingetragen","age":"0","planungsraum":"Bornitzstraße","lat":52.519588686,"lng":13.492770082},{"id":"1409366471888","city":"Berlin","postcode":"10365","employees":"0 Beschäftigte","branch":"Erbringung von sonstigen Dienstleistungen der Informationstechnologie","top_branch":"Erbringung von Dienstleistungen der Informationstechnologie","type":"Kleingewerbetreibender","age":"0","planungsraum":"Bornitzstraße","lat":52.520788482,"lng":13.490669053},{"id":"141139147638","city":"Berlin","postcode":"10365","employees":"unbekannt","branch":"Modedesign","top_branch":"Sonstige wissenschaftliche und technische Tätigkeiten","type":"Kleingewerbetreibender","age":"0","planungsraum":"Bornitzstraße","lat":52.519223977,"lng":13.486899213}]